Workbook

Sheet balance sheet
B2: PT GUNUNG SEMERU
B4: PERKIRAAN BUKU BESAR | D4: DEBET | E4: KREDIT
B5: 100 | C5: Kas Di Bank | D5: 125000000
B6: 101 | C6: Kas Kecil | D6: 5000000
B7: 102 | C7: Piutang Dagang | D7: 11550000
B8: 103 | C8: Persediaan Barang Dagang | D8: 23000000
B9: 104 | C9: Perlengkapan | D9: 2000000
B10: 105 | C10: Sewa Gudang Dibayar Dimuka
B11: 106 | C11: Iklan Dibayar Dimuka
B12: 107 | C12: Asuransi Dibayar Dimuka
B13: 108 | C13: Aktiva Tetap | D13: 3424000000
B14: 109 | C14: Akumulasi Penyusutan Aktiva Tetap | E14: 1064400000
B15: 200 | C15: Utang Dagang | E15: 1540000
B16: 201 | C16: Utang PPH 21 | E16: 80000
B17: 202 | C17: Utang Gaji
B18: 203 | C18: Utang Air, Listrik, dan Telepon
B19: 300 | C19: Modal Saham | E19: 1000000000
B20: 301 | C20: Agio Saham | E20: 156830000
B21: 302 | C21: Laba Ditahan | E21: 400000000
B22: 303 | C22: Ikhtisar Laba Rugi
B23: 400 | C23: Penjualan | E23: 4285000000
B24: 401 | C24: Retur Penjualan | D24: 5000000
B25: 500 | C25: Pembelian | D25: 2857000000
B26: 501 | C26: Retur Pembelian | E26: 7000000
B27: 600 | C27: Beban Perlengkapan Kantor
B28: 601 | C28: Beban Perlengkapan Toko
B29: 602 | C29: Beban Sewa
B30: 603 | C30: Beban Iklan
B31: 604 | C31: Beban Asuransi
B32: 605 | C32: Beban Penyusutan Aktiva Tetap
B33: 606 | C33: Beban Gaji Kantor | D33: 280500000
B34: 607 | C34: Beban Asuransi | D34: 187000000
B35: 608 | C35: Beban Air, Listrik dan Telepon | D35: 9800000
B36: 609 | C36: Beban Administrasi Bank
B37: 610 | C37: Beban PPH 21
B38: 700 | C38: Pendapatan Bunga | E38: 15000000
B39: TOTAL | D39: 6929850000 | E39: 6929850000

Sheet Penyusutan
A1: TAHUN | B1: TANGGAL | D1: BULAN | E1: BULAN DALAM SETAHUN | F1: GEDUNG | G1: AKUMULASI PENUYUSUTAN | H1: NILAI BUKU | J1: TAHUN | K1: TANGGAL | M1: BULAN | N1: BULAN DALAM SETAHUN | O1: PERALATAN | P1: AKUMULASI PENUYUSUTAN | Q1: NILAI BUKU
A3: NILAI PEROLEHAN | F3: 1584000000 | J3: NILAI PEROLEHAN | O3: 360000000
A4: UMUR | F4: 20 | J4: UMUR | O4: 5
A5: PENYUSUTAN PER TAHUN | F5: =F3/F4 -> 79200000 | J5: PENYUSUTAN PER TAHUN | O5: 72000000
A6: 1 | B6: 42036 | C6: 42124 | D6: 3 | E6: 12 | F6: =D6/E6*$F$5 -> 19800000 | G6: =F6 -> 19800000 | H6: =F3-G6 -> 1564200000 | J6: 1 | K6: 41490 | L6: 41759 | M6: =month(L6-K6) -> 9 | N6: 12 | O6: =M6/N6*$O$5 -> 54000000 | P6: =O6 -> 54000000 | Q6: =O3 -> 360000000
A7: 2 | B7: 42125 | C7: 42490 | D7: 12 | E7: 12 | F7: =D7/E7*$F$5 -> 79200000 | G7: =G6+F7 -> 99000000 | H7: =H6-G7 -> 1465200000 | J7: 2 | K7: 41760 | L7: 42124 | M7: =month(L7-K7) -> 12 | N7: 12 | O7: =M7/N7*$O$5 -> 72000000 | P7: =P6+O7 -> 126000000 | Q7: =Q6-P7 -> 234000000
A8: 3 | B8: 42491 | C8: 42855 | D8: 12 | E8: 12 | F8: =D8/E8*$F$5 -> 79200000 | G8: =G7+F8 -> 178200000 | H8: =H7-G8 -> 1287000000 | J8: 3 | K8: 42491 | L8: 42855 | M8: =month(L8-K8) -> 12 | N8: 12 | O8: =M8/N8*$O$5 -> 72000000 | P8: =P7+O8 -> 198000000 | Q8: =Q7-P8 -> 36000000
A9: 4 | B9: =C8+1 -> 42856 | C9: =B9+364 -> 43220 | D9: =month(C9-B9) -> 12 | E9: 12 | F9: =D9/E9*$F$5 -> 79200000 | G9: =G8+F9 -> 257400000 | H9: =H8-G9 -> 1029600000 | J9: 4 | K9: =L8+1 -> 42856 | L9: =K9+364 -> 43220 | M9: =month(L9-K9) -> 12 | N9: 12 | O9: =M9/N9*$O$5 -> 72000000 | P9: =P8+O9 -> 270000000 | Q9: =Q8-P9 -> -234000000
A10: 5 | B10: =C9+1 -> 43221 | C10: =B10+364 -> 43585 | D10: =month(C10-B10) -> 12 | E10: 12 | F10: =D10/E10*$F$5 -> 79200000 | G10: =G9+F10 -> 336600000 | H10: =H9-G10 -> 693000000 | J10: 5 | K10: =L9+1 -> 43221 | L10: =K10+364 -> 43585 | M10: =month(L10-K10) -> 12 | N10: 12 | O10: =M10/N10*$O$5 -> 72000000 | P10: =P9+O10 -> 342000000 | Q10: =Q9-P10 -> -576000000
A12: TAHUN | B12: TANGGAL | D12: BULAN | E12: BULAN DALAM SETAHUN | F12: KENDARAAN | G12: AKUMULASI PENUYUSUTAN | H12: NILAI BUKU
A14: NILAI PEROLEHAN | F14: 480000000
A15: UMUR | F15: 8
A16: PENYUSUTAN PER TAHUN | F16: 60000000
A17: 1 | B17: 40391 | C17: 40663 | D17: =month(C17-B17) -> 9 | E17: 12 | F17: =D17/E17*F$16 -> 45000000 | G17: =F17 -> 45000000 | H17: =F14 -> 480000000
A18: 2 | B18: =C17+1 -> 40664 | C18: =B18+365 -> 41029 | D18: =month(C18-B18) -> 12 | E18: 12 | F18: =D18/E18*F$16 -> 60000000 | G18: =G17+F18 -> 105000000 | H18: =H17-G18 -> 375000000
A19: 3 | B19: =C18+1 -> 41030 | C19: =B19+364 -> 41394 | D19: =month(C19-B19) -> 12 | E19: 12 | F19: =D19/E19*F$16 -> 60000000 | G19: =G18+F19 -> 165000000 | H19: =H18-G19 -> 210000000
A20: 4 | B20: =C19+1 -> 41395 | C20: =B20+364 -> 41759 | D20: =month(C20-B20) -> 12 | E20: 12 | F20: =D20/E20*F$16 -> 60000000 | G20: =G19+F20 -> 225000000 | H20: =H19-G20 -> -15000000
A21: 5 | B21: =C20+1 -> 41760 | C21: =B21+364 -> 42124 | D21: =month(C21-B21) -> 12 | E21: 12 | F21: =D21/E21*F$16 -> 60000000 | G21: =G20+F21 -> 285000000 | H21: =H20-G21 -> -300000000

Sheet Jurnal Umum
C2: PT. GUNUNG SEMERU | K2: PT. GUNUNG SEMERU
F4: No: 01/BKK/GS/IV/2019 | N4: No: 02/BKK/GS/IV/2019
C5: Tanggal : | D5: 43556 | K5: Tanggal : | L5: 43557
C6: Transaksi : | D6: PEMBAYARAN SEWA | K6: Transaksi : | L6: PEMBAYARAN ASURANSI 1 TAHUN
C9: No. Akun | D9: Nama Akun | F9: Debet | G9: Kredit | K9: No. Akun | L9: Nama Akun | N9: Debet | O9: Kredit
C10: 105 | D10: SEWA DIBAYAR DI MUKA | F10: 500000 | K10: 107 | L10: ASURANSI DIBAYAR DI MUKA | N10: 300000
C11: 101 | E11: KAS KECIL | G11: 500000 | K11: 101 | M11: KAS KECIL | O11: 300000
C13: Diperiksa oleh : | E13: Diposting oleh : | G13: Dibuat oleh : | K13: Diperiksa oleh : | M13: Diposting oleh : | O13: Dibuat oleh :
C18: PT. GUNUNG SEMERU | K18: PT. GUNUNG SEMERU
C19: Jl. Pulo Gundul No.12 | K19: Jl. Pulo Gundul No.12
C20: Jakarta Pusat | K20: Jakarta Pusat
C21: BUKU JURNAL | K21: BUKU JURNAL
F23: No: 03/BKK/GS/IV/2019 | N23: No: 04/BKK/GS/IV/2019
C24: Tanggal : | D24: 43557 | K24: Tanggal : | L24: 43564
C25: Transaksi : | D25: PEMBAYARAN IKLAN | K25: Transaksi : | L25: PEMBAYARAN BEBAN LISTRIK AIR DAN TELEPON
C28: No. Akun | D28: Nama Akun | F28: Debet | G28: Kredit | K28: No. Akun | L28: Nama Akun | N28: Debet | O28: Kredit
C29: 106 | D29: IKLAN DIBAYAR DIMUKA | F29: 500000 | K29: 608 | L29: BEBAN AIR LISTRIK DAN TELEPHONE | N29: 450000
C30: 101 | E30: KAS KECIL | G30: 500000 | K30: 101 | M30: KAS KECIL | O30: 450000
C32: Diperiksa oleh : | E32: Diposting oleh : | G32: Dibuat oleh : | K32: Diperiksa oleh : | M32: Diposting oleh : | O32: Dibuat oleh :
C38: PT. GUNUNG SEMERU
C39: Jl. Pulo Gundul No.12
C40: Jakarta Pusat
C41: BUKU JURNAL
F43: No: 05/JU/GS/IV/2019
C44: Tanggal : | D44: 43565
C45: Transaksi : | D45: PEMBAYARAN PPH 21
C48: No. Akun | D48: Nama Akun | F48: Debet | G48: Kredit
C49: 201 | D49: UTANG PPH 21 | F49: 80000
C50: 101 | E50: KAS KECIL | G50: 80000
C52: Diperiksa oleh : | E52: Diposting oleh : | G52: Dibuat oleh :
C57: PT. GUNUNG SEMERU | K57: PT. GUNUNG SEMERU
C58: Jl. Pulo Gundul No.12 | K58: Jl. Pulo Gundul No.12
C59: Jakarta Pusat | K59: Jakarta Pusat
C60: BUKU JURNAL | K60: BUKU JURNAL
F62: No: 01/BKBT/GS/IV/2019 | N62: No: 01/BKBK/GS/IV/2019
C63: Tanggal : | D63: 43560 | K63: Tanggal : | L63: 43564
C64: Transaksi : | D64: 01/BKBT/GS/IV/2019 | K64: Transaksi : | L64: 01/BKBK/GS/IV/2019
C67: No. Akun | D67: Nama Akun | F67: Debet | G67: Kredit | K67: No. Akun | L67: Nama Akun | N67: Debet | O67: Kredit
C68: 100 | D68: KAS | F68: 11550000 | K68: 200 | L68: UTANG DAGANG | N68: 1540000
C69: 102 | E69: PIUTANG | G69: 11550000 | K69: 100 | M69: KAS | O69: 1540000
C71: Diperiksa oleh : | E71: Diposting oleh : | G71: Dibuat oleh : | K71: Diperiksa oleh : | M71: Diposting oleh : | O71: Dibuat oleh :
C76: PT. GUNUNG SEMERU | K76: PT. GUNUNG SEMERU
C77: Jl. Pulo Gundul No.12 | K77: Jl. Pulo Gundul No.12
C78: Jakarta Pusat | K78: Jakarta Pusat
C79: BUKU JURNAL | K79: BUKU JURNAL
F81: No: 6/F/T/IV/2019 | N81: No:01/F/GS/IV/2019
C82: Tanggal : | D82: 43567 | K82: Tanggal : | L82: 43564
C83: Transaksi : | D83: 6/F/T/IV/2019 | K83: Transaksi :
C86: No. Akun | D86: Nama Akun | F86: Debet | G86: Kredit | K86: No. Akun | L86: Nama Akun | N86: Debet | O86: Kredit
C87: 500 | D87: PEMBELIAN | F87: 431200 | K87: 102 | L87: PIUTANG | N87: 1320000
C88: 200 | E88: UTANG | G88: 431200 | K88: 400 | M88: PENJUALAN | O88: 1320000
C90: Diperiksa oleh : | E90: Diposting oleh : | G90: Dibuat oleh : | K90: Diperiksa oleh : | M90: Diposting oleh : | O90: Dibuat oleh :
C95: PT. GUNUNG SEMERU
C96: Jl. Pulo Gundul No.12
C97: Jakarta Pusat
C98: BUKU JURNAL
F100: No: 10/JU/GS/IV/2019
C101: Tanggal : | D101: 43585
C102: Transaksi :
C105: No. Akun | D105: Nama Akun | F105: Debet | G105: Kredit
C106: 102 | D106: PIUTANG | F106: 3300000
C107: 400 | E107: PENJUALAN | G107: 3300000
C110: Diperiksa oleh : | E110: Diposting oleh : | G110: Dibuat oleh :
C117: Recapitulation
C118: No. Akun | D118: Debet | E118: Kredit
C119: 100 | D119: 11550000 | E119: 1540000
C120: 101 | D120: 0 | E120: 1830000
C121: 102 | D121: 2640000 | E121: 11550000
C122: 105 | D122: 500000 | E122: 0
C123: 106 | D123: 500000 | E123: 0
C124: 107 | D124: 300000 | E124: 0
C125: 200 | D125: 1540000 | E125: 431200
C126: 201 | D126: 80000 | E126: 0
C127: 400 | D127: 0 | E127: 2640000
C128: 500 | D128: 431200 | E128: 0
C129: 608 | D129: 450000 | E129: 0
D130: =SUM(D118:D129) -> 17991200 | E130: =SUM(E118:E129) -> 17991200

Sheet Buku Besar
B3: Account: | E3: GENERAL LEDGER | I3: Account Number: | K3: Account: | N3: GENERAL LEDGER | R3: Account Number: | T3: Account: | W3: GENERAL LEDGER | AA3: Account Number:
D4: Kas Kecil | I4: {=xLOOKUP(D4,'balance sheet'!$C$5:$C$38,'balance sheet'!$B$5:$B$38)} -> 101 | K4: Utang Dagang | R4: {=xLOOKUP(K4,'balance sheet'!$C$5:$C$38,'balance sheet'!$B$5:$B$38)} -> 200 | T4: Beban Perlengkapan Kantor | AA4: {=xLOOKUP(T4,'balance sheet'!$C$5:$C$38,'balance sheet'!$B$5:$B$38)} -> 600
B5: Date | D5: Description | E5: Ref. | F5: Debet | G5: Credit | H5: Balance | K5: Date | M5: Description | N5: Ref. | O5: Debet | P5: Credit | Q5: Balance | T5: Date | V5: Description | W5: Ref. | X5: Debet | Y5: Credit | Z5: Balance
H6: Debet | I6: Credit | Q6: Debet | R6: Credit | Z6: Debet | AA6: Credit
B7: Dec | C7: 1 | D7: Opening Balance | H7: {=XLOOKUP(I4,'balance sheet'!B:B,'balance sheet'!D:D)} -> 5000000 | K7: Dec | L7: 1 | M7: Opening Balance | Q7: {=XLOOKUP(R4,'balance sheet'!$B:$B,'balance sheet'!$E:$E)} -> 1540000 | T7: Dec | U7: 1 | V7: Opening Balance | Z7: {=XLOOKUP(AA4,'balance sheet'!$B:$B,'balance sheet'!$E:$E)}
C8: 31 | E8: JU | F8: =SUMIF('Jurnal Umum'!$C$119:$C$130,I4,'Jurnal Umum'!$D$119:$D$130) -> 0 | G8: =SUMIF('Jurnal Umum'!$C$119:$C$130,I4,'Jurnal Umum'!$E$119:$E$130) -> 1830000 | H8: =H7+F8-G8 -> 3170000 | I8: =IF(H7="",I7+G8-F8,"") | L8: 31 | N8: JU | O8: =SUMIF('Jurnal Umum'!$C$119:$C$130,R4,'Jurnal Umum'!$D$119:$D$130) -> 1540000 | P8: =SUMIF('Jurnal Umum'!$C$119:$C$130,R4,'Jurnal Umum'!$E$119:$E$130) -> 431200 | Q8: =Q7+O8-P8 -> 2648800 | R8: =IF(Q7="",R7+P8-O8,"") | U8: 31 | W8: JU | X8: =SUMIF('Jurnal Umum'!$C$119:$C$130,AA4,'Jurnal Umum'!$D$119:$D$130) -> 0 | Y8: =SUMIF('Jurnal Umum'!$C$119:$C$130,AA4,'Jurnal Umum'!$E$119:$E$130) -> 0 | Z8: =Z7+X8-Y8 -> 0 | AA8: =IF(Z7="",AA7+Y8-X8,"") -> 0
C9: 31 | E9: JP | F9: =SUMIF('Jurnal Penyesuai'!$R$4:$R$21,I4,'Jurnal Penyesuai'!$S$4:$S$21) -> 0 | G9: =SUMIF('Jurnal Penyesuai'!$R$4:$R$21,I4,'Jurnal Penyesuai'!$T$4:$T$21) -> 0 | H9: =H8+F9-G9 -> 3170000 | I9: =IF(H8="",I8+G9-F9,"") | L9: 31 | N9: JP | O9: =SUMIF('Jurnal Penyesuai'!$R$4:$R$21,R4,'Jurnal Penyesuai'!$S$4:$S$21) -> 0 | P9: =SUMIF('Jurnal Penyesuai'!$R$4:$R$21,R4,'Jurnal Penyesuai'!$T$4:$T$21) -> 0 | Q9: =Q8+O9-P9 -> 2648800 | R9: =IF(Q8="",R8+P9-O9,"") | U9: 31 | W9: JP | X9: =SUMIF('Jurnal Penyesuai'!$R$4:$R$21,AA4,'Jurnal Penyesuai'!$S$4:$S$21) -> 780000 | Y9: =SUMIF('Jurnal Penyesuai'!$R$4:$R$21,AA4,'Jurnal Penyesuai'!$T$4:$T$21) -> 0 | Z9: =Z8+X9-Y9 -> 780000 | AA9: =IF(Z8="",AA8+Y9-X9,"")
B12: Account: | E12: GENERAL LEDGER | I12: Account Number: | K12: Account: | N12: GENERAL LEDGER | R12: Account Number: | T12: Account: | W12: GENERAL LEDGER | AA12: Account Number:
D13: Kas Di Bank | I13: {=xLOOKUP(D13,'balance sheet'!$C$5:$C$38,'balance sheet'!$B$5:$B$38)} -> 100 | K13: Utang PPH 21 | R13: {=xLOOKUP(K13,'balance sheet'!$C$5:$C$38,'balance sheet'!$B$5:$B$38)} -> 201 | T13: Beban Perlengkapan Toko | AA13: {=xLOOKUP(T13,'balance sheet'!$C$5:$C$38,'balance sheet'!$B$5:$B$38)} -> 601
B14: Date | D14: Description | E14: Ref. | F14: Debet | G14: Credit | H14: Balance | K14: Date | M14: Description | N14: Ref. | O14: Debet | P14: Credit | Q14: Balance | T14: Date | V14: Description | W14: Ref. | X14: Debet | Y14: Credit | Z14: Balance
H15: Debet | I15: Credit | Q15: Debet | R15: Credit | Z15: Debet | AA15: Credit
B16: Dec | C16: 1 | D16: Opening Balance | H16: {=XLOOKUP(I13,'balance sheet'!B:B,'balance sheet'!D:D)} -> 125000000 | K16: Dec | L16: 1 | M16: Opening Balance | Q16: {=XLOOKUP(R13,'balance sheet'!$B:$B,'balance sheet'!$E:$E)} -> 80000 | T16: Dec | U16: 1 | V16: Opening Balance | Z16: {=XLOOKUP(AA13,'balance sheet'!$B:$B,'balance sheet'!$E:$E)}
C17: 31 | E17: JU | F17: =SUMIF('Jurnal Umum'!$C$119:$C$130,I13,'Jurnal Umum'!$D$119:$D$130) -> 11550000 | G17: =SUMIF('Jurnal Umum'!$C$119:$C$130,I13,'Jurnal Umum'!$E$119:$E$130) -> 1540000 | H17: =H16+F17-G17 -> 135010000 | I17: =IF(H16="",I16+G17-F17,"") | L17: 31 | N17: JU | O17: =SUMIF('Jurnal Umum'!$C$119:$C$130,R13,'Jurnal Umum'!$D$119:$D$130) -> 80000 | P17: =SUMIF('Jurnal Umum'!$C$119:$C$130,R13,'Jurnal Umum'!$E$119:$E$130) -> 0 | Q17: =Q16+O17-P17 -> 160000 | R17: =IF(and(Q16="",O16="",P16=""),"",IF(R16+P17-O17<0,"","")) | U17: 31 | W17: JU | X17: =SUMIF('Jurnal Umum'!$C$119:$C$130,AA13,'Jurnal Umum'!$D$119:$D$130) -> 0 | Y17: =SUMIF('Jurnal Umum'!$C$119:$C$130,AA13,'Jurnal Umum'!$E$119:$E$130) -> 0 | Z17: =Z16+X17-Y17 -> 0 | AA17: =IF(and(Z16="",X16="",Y16=""),"",AA16+Y17-X17)
C18: 31 | E18: JP | F18: =SUMIF('Jurnal Penyesuai'!$R$4:$R$21,I13,'Jurnal Penyesuai'!$S$4:$S$21) -> 990000 | G18: =SUMIF('Jurnal Penyesuai'!$R$4:$R$21,I13,'Jurnal Penyesuai'!$T$4:$T$21) -> 0 | H18: =H17+F18-G18 -> 136000000 | I18: =IF(H17="",I17+G18-F18,"") | L18: 31 | N18: JP | O18: =SUMIF('Jurnal Penyesuai'!$R$4:$R$21,R13,'Jurnal Penyesuai'!$S$4:$S$21) -> 0 | P18: =SUMIF('Jurnal Penyesuai'!$R$4:$R$21,R13,'Jurnal Penyesuai'!$T$4:$T$21) -> 80000 | Q18: =Q17+O18-P18 -> 80000 | R18: =IF(Q17="",R17+P18-O18,"") | U18: 31 | W18: JP | X18: =SUMIF('Jurnal Penyesuai'!$R$4:$R$21,AA13,'Jurnal Penyesuai'!$S$4:$S$21) -> 520000 | Y18: =SUMIF('Jurnal Penyesuai'!$R$4:$R$21,AA13,'Jurnal Penyesuai'!$T$4:$T$21) -> 0 | Z18: =Z17+X18-Y18 -> 520000 | AA18: =IF(Z17="",AA17+Y18-X18,"")
B21: Account: | E21: GENERAL LEDGER | I21: Account Number: | K21: Account: | N21: GENERAL LEDGER | R21: Account Number: | T21: Account: | W21: GENERAL LEDGER | AA21: Account Number:
B22: Piutang Dagang | I22: {=xLOOKUP(B22,'balance sheet'!$C$5:$C$38,'balance sheet'!$B$5:$B$38)} -> 102 | K22: Utang Gaji | R22: {=xLOOKUP(K22,'balance sheet'!$C$5:$C$38,'balance sheet'!$B$5:$B$38)} -> 202 | T22: Beban Sewa | AA22: {=xLOOKUP(T22,'balance sheet'!$C$5:$C$38,'balance sheet'!$B$5:$B$38)} -> 602
B23: Date | D23: Description | E23: Ref. | F23: Debet | G23: Credit | H23: Balance | K23: Date | M23: Description | N23: Ref. | O23: Debet | P23: Credit | Q23: Balance | T23: Date | V23: Description | W23: Ref. | X23: Debet | Y23: Credit | Z23: Balance
H24: Debet | I24: Credit | Q24: Debet | R24: Credit | Z24: Debet | AA24: Credit
B25: Dec | C25: 1 | D25: Opening Balance | H25: {=XLOOKUP(I22,'balance sheet'!B:B,'balance sheet'!D:D)} -> 11550000 | K25: Dec | L25: 1 | M25: Opening Balance | Q25: {=XLOOKUP(R22,'balance sheet'!$B:$B,'balance sheet'!$E:$E)} | U25: 31 | V25: Opening Balance | X25: =SUMIF('Jurnal Umum'!$C$119:$C$130,AA21,'Jurnal Umum'!$D$119:$D$130) -> 0 | Y25: =SUMIF('Jurnal Umum'!$C$119:$C$130,AA21,'Jurnal Umum'!$E$119:$E$130) -> 0 | Z25: {=XLOOKUP(AA22,'balance sheet'!$B:$B,'balance sheet'!$E:$F)}
C26: 31 | E26: JU | F26: =SUMIF('Jurnal Umum'!$C$119:$C$130,I22,'Jurnal Umum'!$D$119:$D$130) -> 2640000 | G26: =SUMIF('Jurnal Umum'!$C$119:$C$130,I22,'Jurnal Umum'!$E$119:$E$130) -> 11550000 | H26: =H25+F26-G26 -> 2640000 | I26: =IF(H25="",I25+G26-F26,"") | L26: 31 | N26: JU | O26: =SUMIF('Jurnal Umum'!$C$119:$C$130,R22,'Jurnal Umum'!$D$119:$D$130) -> 0 | P26: =SUMIF('Jurnal Umum'!$C$119:$C$130,R22,'Jurnal Umum'!$E$119:$E$130) -> 0 | Q26: =Q25+O26-P26 -> 0 | R26: =IF(and(Q25="",O25="",P25=""),"",IF(R25+P26-O26<0,"","")) | U26: 31 | W26: JU | X26: =SUMIF('Jurnal Umum'!$C$119:$C$130,AA22,'Jurnal Umum'!$D$119:$D$130) -> 0 | Y26: =SUMIF('Jurnal Umum'!$C$119:$C$130,AA22,'Jurnal Umum'!$E$119:$E$130) -> 0 | Z26: =Z25+X26-Y26 -> 0 | AA26: =IF(and(Z25="",X25="",Y25=""),"",AA25+Y26-X26) -> 0
C27: 31 | E27: JP | F27: =SUMIF('Jurnal Penyesuai'!$R$4:$R$21,I22,'Jurnal Penyesuai'!$S$4:$S$21) -> 0 | G27: =SUMIF('Jurnal Penyesuai'!$R$4:$R$21,I22,'Jurnal Penyesuai'!$T$4:$T$21) -> 0 | H27: =H26+F27-G27 -> 2640000 | I27: =IF(H26="",I26+G27-F27,"") | L27: 31 | N27: JP | O27: =SUMIF('Jurnal Penyesuai'!$R$4:$R$21,R22,'Jurnal Penyesuai'!$S$4:$S$21) -> 0 | P27: =SUMIF('Jurnal Penyesuai'!$R$4:$R$21,R22,'Jurnal Penyesuai'!$T$4:$T$21) -> 0 | Q27: =Q26+O27-P27 -> 0 | R27: =IF(Q26="",R26+P27-O27,"") | U27: 31 | W27: JP | X27: =SUMIF('Jurnal Penyesuai'!$R$4:$R$21,AA22,'Jurnal Penyesuai'!$S$4:$S$21) -> 500000 | Y27: =SUMIF('Jurnal Penyesuai'!$R$4:$R$21,AA22,'Jurnal Penyesuai'!$T$4:$T$21) -> 0 | Z27: =Z26+X27-Y27 -> 500000 | AA27: =IF(Z26="",AA26+Y27-X27,"")
B30: Account: | E30: GENERAL LEDGER | I30: Account Number: | K30: Account: | N30: GENERAL LEDGER | R30: Account Number: | T30: Account: | W30: GENERAL LEDGER | AA30: Account Number:
B31: Persediaan Barang Dagang | I31: {=xLOOKUP(B31,'balance sheet'!$C$5:$C$38,'balance sheet'!$B$5:$B$38)} -> 103 | K31: Modal Saham | R31: {=xLOOKUP(K31,'balance sheet'!$C$5:$C$38,'balance sheet'!$B$5:$B$38)} -> 300 | T31: Beban Iklan | AA31: {=xLOOKUP(T31,'balance sheet'!$C$5:$C$38,'balance sheet'!$B$5:$B$38)} -> 603
B32: Date | D32: Description | E32: Ref. | F32: Debet | G32: Credit | H32: Balance | K32: Date | M32: Description | N32: Ref. | O32: Debet | P32: Credit | Q32: Balance | T32: Date | V32: Description | W32: Ref. | X32: Debet | Y32: Credit | Z32: Balance
H33: Debet | I33: Credit | Q33: Debet | R33: Credit | Z33: Debet | AA33: Credit
B34: Dec | C34: 1 | D34: Opening Balance | H34: {=XLOOKUP(I31,'balance sheet'!B:B,'balance sheet'!D:D)} -> 23000000 | K34: Dec | L34: 1 | M34: Opening Balance | Q34: {=XLOOKUP(R31,'balance sheet'!$B:$B,'balance sheet'!$D:$E)} | R34: 1000000000 | U34: 31 | V34: Opening Balance | X34: =SUMIF('Jurnal Umum'!$C$119:$C$130,AA30,'Jurnal Umum'!$D$119:$D$130) -> 0 | Y34: =SUMIF('Jurnal Umum'!$C$119:$C$130,AA30,'Jurnal Umum'!$E$119:$E$130) -> 0 | Z34: {=XLOOKUP(AA31,'balance sheet'!$B:$B,'balance sheet'!$E:$F)}
C35: 31 | E35: JU | F35: =SUMIF('Jurnal Umum'!$C$119:$C$130,I31,'Jurnal Umum'!$D$119:$D$130) -> 0 | G35: =SUMIF('Jurnal Umum'!$C$119:$C$130,I31,'Jurnal Umum'!$E$119:$E$130) -> 0 | H35: =H34+F35-G35 -> 23000000 | I35: =IF(H34="",I34+G35-F35,"") | L35: 31 | N35: JU | O35: =SUMIF('Jurnal Umum'!$C$119:$C$130,R31,'Jurnal Umum'!$D$119:$D$130) -> 0 | P35: =SUMIF('Jurnal Umum'!$C$119:$C$130,R31,'Jurnal Umum'!$E$119:$E$130) -> 0 | Q35: =Q34+O35-P35 -> 0 | R35: =IF(and(Q34="",O34="",P34=""),"",IF(R34+P35-O35<0,"","")) | U35: 31 | W35: JU | X35: =SUMIF('Jurnal Umum'!$C$119:$C$130,AA31,'Jurnal Umum'!$D$119:$D$130) -> 0 | Y35: =SUMIF('Jurnal Umum'!$C$119:$C$130,AA31,'Jurnal Umum'!$E$119:$E$130) -> 0 | Z35: =Z34+X35-Y35 -> 0 | AA35: =IF(and(Z34="",X34="",Y34=""),"",AA34+Y35-X35) -> 0
C36: 31 | E36: JP | F36: =SUMIF('Jurnal Penyesuai'!$R$4:$R$21,I31,'Jurnal Penyesuai'!$S$4:$S$21) -> 20300000 | G36: =SUMIF('Jurnal Penyesuai'!$R$4:$R$21,I31,'Jurnal Penyesuai'!$T$4:$T$21) -> 22450000 | H36: =H35+F36-G36 -> 20850000 | I36: =IF(H35="",I35+G36-F36,"") | L36: 31 | N36: JP | O36: =SUMIF('Jurnal Penyesuai'!$R$4:$R$21,R31,'Jurnal Penyesuai'!$S$4:$S$21) -> 0 | P36: =SUMIF('Jurnal Penyesuai'!$R$4:$R$21,R31,'Jurnal Penyesuai'!$T$4:$T$21) -> 0 | Q36: =Q35+O36-P36 -> 0 | R36: =IF(Q35="",R35+P36-O36,"") | U36: 31 | W36: JP | X36: =SUMIF('Jurnal Penyesuai'!$R$4:$R$21,AA31,'Jurnal Penyesuai'!$S$4:$S$21) -> 400000 | Y36: =SUMIF('Jurnal Penyesuai'!$R$4:$R$21,AA31,'Jurnal Penyesuai'!$T$4:$T$21) -> 0 | Z36: =Z35+X36-Y36 -> 400000 | AA36: =IF(Z35="",AA35+Y36-X36,"")
B39: Account: | E39: GENERAL LEDGER | I39: Account Number: | K39: Account: | N39: GENERAL LEDGER | R39: Account Number: | T39: Account: | W39: GENERAL LEDGER | AA39: Account Number:
B40: Perlengkapan | I40: {=xLOOKUP(B40,'balance sheet'!$C$5:$C$38,'balance sheet'!$B$5:$B$38)} -> 104 | K40: Agio Saham | R40: {=xLOOKUP(K40,'balance sheet'!$C$5:$C$38,'balance sheet'!$B$5:$B$38)} -> 301 | T40: Beban Asuransi | AA40: {=xLOOKUP(T40,'balance sheet'!$C$5:$C$38,'balance sheet'!$B$5:$B$38)} -> 604
B41: Date | D41: Description | E41: Ref. | F41: Debet | G41: Credit | H41: Balance | K41: Date | M41: Description | N41: Ref. | O41: Debet | P41: Credit | Q41: Balance | T41: Date | V41: Description | W41: Ref. | X41: Debet | Y41: Credit | Z41: Balance
H42: Debet | I42: Credit | Q42: Debet | R42: Credit | Z42: Debet | AA42: Credit
B43: Dec | C43: 1 | D43: Opening Balance | H43: {=XLOOKUP(I40,'balance sheet'!B:B,'balance sheet'!D:D)} -> 2000000 | K43: Dec | L43: 1 | M43: Opening Balance | Q43: {=XLOOKUP(R40,'balance sheet'!$B:$B,'balance sheet'!$D:$E)} | R43: 156830000 | U43: 31 | V43: Opening Balance | X43: =SUMIF('Jurnal Umum'!$C$119:$C$130,AA39,'Jurnal Umum'!$D$119:$D$130) -> 0 | Y43: =SUMIF('Jurnal Umum'!$C$119:$C$130,AA39,'Jurnal Umum'!$E$119:$E$130) -> 0 | Z43: {=XLOOKUP(AA40,'balance sheet'!$B:$B,'balance sheet'!$E:$F)}
C44: 31 | E44: JU | F44: =SUMIF('Jurnal Umum'!$C$119:$C$130,I40,'Jurnal Umum'!$D$119:$D$130) -> 0 | G44: =SUMIF('Jurnal Umum'!$C$119:$C$130,I40,'Jurnal Umum'!$E$119:$E$130) -> 0 | H44: =H43+F44-G44 -> 2000000 | I44: =IF(H43="",I43+G44-F44,"") | L44: 31 | N44: JU | O44: =SUMIF('Jurnal Umum'!$C$119:$C$130,R40,'Jurnal Umum'!$D$119:$D$130) -> 0 | P44: =SUMIF('Jurnal Umum'!$C$119:$C$130,R40,'Jurnal Umum'!$E$119:$E$130) -> 0 | Q44: =Q43+O44-P44 -> 0 | R44: =IF(and(Q43="",O43="",P43=""),"",IF(R43+P44-O44<0,"","")) | U44: 31 | W44: JU | X44: =SUMIF('Jurnal Umum'!$C$119:$C$130,AA40,'Jurnal Umum'!$D$119:$D$130) -> 0 | Y44: =SUMIF('Jurnal Umum'!$C$119:$C$130,AA40,'Jurnal Umum'!$E$119:$E$130) -> 0 | Z44: =Z43+X44-Y44 -> 0 | AA44: =IF(and(Z43="",X43="",Y43=""),"",AA43+Y44-X44) -> 0
C45: 31 | E45: JP | F45: =SUMIF('Jurnal Penyesuai'!$R$4:$R$21,I40,'Jurnal Penyesuai'!$S$4:$S$21) -> 0 | G45: =SUMIF('Jurnal Penyesuai'!$R$4:$R$21,I40,'Jurnal Penyesuai'!$T$4:$T$21) -> 1300000 | H45: =H44+F45-G45 -> 700000 | I45: =IF(H44="",I44+G45-F45,"") | L45: 31 | N45: JP | O45: =SUMIF('Jurnal Penyesuai'!$R$4:$R$21,R40,'Jurnal Penyesuai'!$S$4:$S$21) -> 0 | P45: =SUMIF('Jurnal Penyesuai'!$R$4:$R$21,R40,'Jurnal Penyesuai'!$T$4:$T$21) -> 0 | Q45: =Q44+O45-P45 -> 0 | R45: =IF(Q44="",R44+P45-O45,"") | U45: 31 | W45: JP | X45: =SUMIF('Jurnal Penyesuai'!$R$4:$R$21,AA40,'Jurnal Penyesuai'!$S$4:$S$21) -> 25000 | Y45: =SUMIF('Jurnal Penyesuai'!$R$4:$R$21,AA40,'Jurnal Penyesuai'!$T$4:$T$21) -> 0 | Z45: =Z44+X45-Y45 -> 25000 | AA45: =IF(Z44="",AA44+Y45-X45,"")
B48: Account: | E48: GENERAL LEDGER | I48: Account Number: | K48: Account: | N48: GENERAL LEDGER | R48: Account Number: | T48: Account: | W48: GENERAL LEDGER | AA48: Account Number:
B49: Sewa Gudang Dibayar Dimuka | I49: {=xLOOKUP(B49,'balance sheet'!$C$5:$C$38,'balance sheet'!$B$5:$B$38)} -> 105 | K49: Laba Ditahan | R49: {=xLOOKUP(K49,'balance sheet'!$C$5:$C$38,'balance sheet'!$B$5:$B$38)} -> 302 | T49: Beban Penyusutan Aktiva Tetap | AA49: {=xLOOKUP(T49,'balance sheet'!$C$5:$C$38,'balance sheet'!$B$5:$B$38)} -> 605
B50: Date | D50: Description | E50: Ref. | F50: Debet | G50: Credit | H50: Balance | K50: Date | M50: Description | N50: Ref. | O50: Debet | P50: Credit | Q50: Balance | T50: Date | V50: Description | W50: Ref. | X50: Debet | Y50: Credit | Z50: Balance
H51: Debet | I51: Credit | Q51: Debet | R51: Credit | Z51: Debet | AA51: Credit
B52: Dec | C52: 1 | D52: Opening Balance | H52: {=XLOOKUP(I49,'balance sheet'!B:B,'balance sheet'!D:D)} | K52: Dec | L52: 1 | M52: Opening Balance | Q52: {=XLOOKUP(R49,'balance sheet'!$B:$B,'balance sheet'!$D:$E)} | R52: 400000000 | T52: Dec | U52: 1 | V52: Opening Balance | Z52: {=XLOOKUP(AA49,'balance sheet'!$B:$B,'balance sheet'!$D:$E)}
C53: 31 | E53: JU | F53: =SUMIF('Jurnal Umum'!$C$119:$C$130,I49,'Jurnal Umum'!$D$119:$D$130) -> 500000 | G53: =SUMIF('Jurnal Umum'!$C$119:$C$130,I49,'Jurnal Umum'!$E$119:$E$130) -> 0 | H53: =H52+F53-G53 -> 500000 | I53: =IF(H52="",I52+G53-F53,"") -> -500000 | L53: 31 | N53: JU | O53: =SUMIF('Jurnal Umum'!$C$119:$C$130,R49,'Jurnal Umum'!$D$119:$D$130) -> 0 | P53: =SUMIF('Jurnal Umum'!$C$119:$C$130,R49,'Jurnal Umum'!$E$119:$E$130) -> 0 | Q53: =Q52+O53-P53 -> 0 | R53: =IF(and(Q52="",O52="",P52=""),"",IF(R52+P53-O53<0,"","")) | U53: 31 | W53: JU | X53: =SUMIF('Jurnal Umum'!$C$119:$C$130,AA49,'Jurnal Umum'!$D$119:$D$130) -> 0 | Y53: =SUMIF('Jurnal Umum'!$C$119:$C$130,AA49,'Jurnal Umum'!$E$119:$E$130) -> 0 | Z53: =Z52+X53-Y53 -> 0 | AA53: =IF(and(Z52="",X52="",Y52=""),"",AA52+Y53-X53)
C54: 31 | E54: JP | F54: =SUMIF('Jurnal Penyesuai'!$R$4:$R$21,I49,'Jurnal Penyesuai'!$S$4:$S$21) -> 0 | G54: =SUMIF('Jurnal Penyesuai'!$R$4:$R$21,I49,'Jurnal Penyesuai'!$T$4:$T$21) -> 500000 | H54: =H53+F54-G54 -> 0 | I54: =IF(H53="",I53+G54-F54,"") | L54: 31 | N54: JP | O54: =SUMIF('Jurnal Penyesuai'!$R$4:$R$21,R49,'Jurnal Penyesuai'!$S$4:$S$21) -> 0 | P54: =SUMIF('Jurnal Penyesuai'!$R$4:$R$21,R49,'Jurnal Penyesuai'!$T$4:$T$21) -> 0 | Q54: =Q53+O54-P54 -> 0 | R54: =IF(Q53="",R53+P54-O54,"") | U54: 31 | W54: JP | X54: =SUMIF('Jurnal Penyesuai'!$R$4:$R$21,AA49,'Jurnal Penyesuai'!$S$4:$S$21) -> 336600000 | Y54: =SUMIF('Jurnal Penyesuai'!$R$4:$R$21,AA49,'Jurnal Penyesuai'!$T$4:$T$21) -> 0 | Z54: =Z53+X54-Y54 -> 336600000 | AA54: =IF(Z53="",AA53+Y54-X54,"")
B57: Account: | E57: GENERAL LEDGER | I57: Account Number: | K57: Account: | N57: GENERAL LEDGER | R57: Account Number: | T57: Account: | W57: GENERAL LEDGER | AA57: Account Number:
B58: Iklan Dibayar Dimuka | I58: {=xLOOKUP(B58,'balance sheet'!$C$5:$C$38,'balance sheet'!$B$5:$B$38)} -> 106 | K58: Penjualan | R58: {=xLOOKUP(K58,'balance sheet'!$C$5:$C$38,'balance sheet'!$B$5:$B$38)} -> 400 | T58: Beban Gaji Kantor | AA58: {=xLOOKUP(T58,'balance sheet'!$C$5:$C$38,'balance sheet'!$B$5:$B$38)} -> 606
B59: Date | D59: Description | E59: Ref. | F59: Debet | G59: Credit | H59: Balance | K59: Date | M59: Description | N59: Ref. | O59: Debet | P59: Credit | Q59: Balance | T59: Date | V59: Description | W59: Ref. | X59: Debet | Y59: Credit | Z59: Balance
H60: Debet | I60: Credit | Q60: Debet | R60: Credit | Z60: Debet | AA60: Credit
B61: Dec | C61: 1 | D61: Opening Balance | H61: {=XLOOKUP(I58,'balance sheet'!B:B,'balance sheet'!D:D)} | K61: Dec | L61: 1 | M61: Opening Balance | Q61: {=XLOOKUP(R58,'balance sheet'!$B:$B,'balance sheet'!$D:$E)} | R61: 4285000000 | T61: Dec | U61: 1 | V61: Opening Balance | Z61: {=XLOOKUP(AA58,'balance sheet'!$B:$B,'balance sheet'!$D:$E)} -> 280500000
C62: 31 | E62: JU | F62: =SUMIF('Jurnal Umum'!$C$119:$C$130,I58,'Jurnal Umum'!$D$119:$D$130) -> 500000 | G62: =SUMIF('Jurnal Umum'!$C$119:$C$130,I58,'Jurnal Umum'!$E$119:$E$130) -> 0 | H62: =H61+F62-G62 -> 500000 | I62: =IF(I61+G62-F62<0,"",I61+G62-F62) | L62: 31 | N62: JU | O62: =SUMIF('Jurnal Umum'!$C$119:$C$130,R58,'Jurnal Umum'!$D$119:$D$130) -> 0 | P62: =SUMIF('Jurnal Umum'!$C$119:$C$130,R58,'Jurnal Umum'!$E$119:$E$130) -> 2640000 | Q62: =Q61+O62-P62 -> -2640000 | R62: =IF(and(Q61="",O61="",P61=""),"",IF(R61+P62-O62<0,"","")) | U62: 31 | W62: JU | X62: =SUMIF('Jurnal Umum'!$C$119:$C$130,AA58,'Jurnal Umum'!$D$119:$D$130) -> 0 | Y62: =SUMIF('Jurnal Umum'!$C$119:$C$130,AA58,'Jurnal Umum'!$E$119:$E$130) -> 0 | Z62: =Z61+X62-Y62 -> 280500000 | AA62: =IF(and(Z61="",X61="",Y61=""),"",AA61+Y62-X62) -> 0
C63: 31 | E63: JP | F63: =SUMIF('Jurnal Penyesuai'!$R$4:$R$21,I58,'Jurnal Penyesuai'!$S$4:$S$21) -> 0 | G63: =SUMIF('Jurnal Penyesuai'!$R$4:$R$21,I58,'Jurnal Penyesuai'!$T$4:$T$21) -> 400000 | H63: =H62+F63-G63 -> 100000 | I63: =IF(H62="",I62+G63-F63,"") | L63: 31 | N63: JP | O63: =SUMIF('Jurnal Penyesuai'!$R$4:$R$21,R58,'Jurnal Penyesuai'!$S$4:$S$21) -> 0 | P63: =SUMIF('Jurnal Penyesuai'!$R$4:$R$21,R58,'Jurnal Penyesuai'!$T$4:$T$21) -> 0 | Q63: =Q62+O63-P63 -> -2640000 | R63: =IF(Q62="",R62+P63-O63,"") | U63: 31 | W63: JP | X63: =SUMIF('Jurnal Penyesuai'!$R$4:$R$21,AA58,'Jurnal Penyesuai'!$S$4:$S$21) -> 0 | Y63: =SUMIF('Jurnal Penyesuai'!$R$4:$R$21,AA58,'Jurnal Penyesuai'!$T$4:$T$21) -> 0 | Z63: =Z62+X63-Y63 -> 280500000 | AA63: =IF(Z62="",AA62+Y63-X63,"")
B66: Account: | E66: GENERAL LEDGER | I66: Account Number: | K66: Account: | N66: GENERAL LEDGER | R66: Account Number: | T66: Account: | W66: GENERAL LEDGER | AA66: Account Number:
B67: Asuransi Dibayar Dimuka | I67: {=xLOOKUP(B67,'balance sheet'!$C$5:$C$38,'balance sheet'!$B$5:$B$38)} -> 107 | K67: Retur Penjualan | R67: {=xLOOKUP(K67,'balance sheet'!$C$5:$C$38,'balance sheet'!$B$5:$B$38)} -> 401 | T67: Beban Asuransi | AA67: 607
B68: Date | D68: Description | E68: Ref. | F68: Debet | G68: Credit | H68: Balance | K68: Date | M68: Description | N68: Ref. | O68: Debet | P68: Credit | Q68: Balance | T68: Date | V68: Description | W68: Ref. | X68: Debet | Y68: Credit | Z68: Balance
H69: Debet | I69: Credit | Q69: Debet | R69: Credit | Z69: Debet | AA69: Credit
B70: Dec | C70: 1 | D70: Opening Balance | H70: {=XLOOKUP(I67,'balance sheet'!B:B,'balance sheet'!D:D)} | K70: Dec | L70: 1 | M70: Opening Balance | Q70: {=XLOOKUP(R67,'balance sheet'!$B:$B,'balance sheet'!$D:$E)} -> 5000000 | T70: Dec | U70: 1 | V70: Opening Balance | Z70: 9800000
C71: 31 | E71: JU | F71: =SUMIF('Jurnal Umum'!$C$119:$C$130,I67,'Jurnal Umum'!$D$119:$D$130) -> 300000 | G71: =SUMIF('Jurnal Umum'!$C$119:$C$130,I67,'Jurnal Umum'!$E$119:$E$130) -> 0 | H71: =H70+F71-G71 -> 300000 | I71: =IF(I70+G71-F71<0,"",I70+G71-F71) | L71: 31 | N71: JU | O71: =SUMIF('Jurnal Umum'!$C$119:$C$130,R67,'Jurnal Umum'!$D$119:$D$130) -> 0 | P71: =SUMIF('Jurnal Umum'!$C$119:$C$130,R67,'Jurnal Umum'!$E$119:$E$130) -> 0 | Q71: =Q70+O71-P71 -> 5000000 | R71: =IF(and(Q70="",O70="",P70=""),"",IF(R70+P71-O71<0,"","")) | U71: 31 | W71: JU | X71: =SUMIF('Jurnal Umum'!$C$119:$C$130,AA67,'Jurnal Umum'!$D$119:$D$130) -> 0 | Y71: =SUMIF('Jurnal Umum'!$C$119:$C$130,AA67,'Jurnal Umum'!$E$119:$E$130) -> 0 | Z71: =Z70+X71-Y71 -> 9800000 | AA71: =IF(and(Z70="",X70="",Y70=""),"",AA70+Y71-X71) -> 0
C72: 31 | E72: JP | F72: =SUMIF('Jurnal Penyesuai'!$R$4:$R$21,I67,'Jurnal Penyesuai'!$S$4:$S$21) -> 0 | G72: =SUMIF('Jurnal Penyesuai'!$R$4:$R$21,I67,'Jurnal Penyesuai'!$T$4:$T$21) -> 25000 | H72: =H71+F72-G72 -> 275000 | I72: =IF(H71="",I71+G72-F72,"") | L72: 31 | N72: JP | O72: =SUMIF('Jurnal Penyesuai'!$R$4:$R$21,R67,'Jurnal Penyesuai'!$S$4:$S$21) -> 0 | P72: =SUMIF('Jurnal Penyesuai'!$R$4:$R$21,R67,'Jurnal Penyesuai'!$T$4:$T$21) -> 0 | Q72: =Q71+O72-P72 -> 5000000 | R72: =IF(Q71="",R71+P72-O72,"") | U72: 31 | W72: JP | X72: =SUMIF('Jurnal Penyesuai'!$R$4:$R$21,AA67,'Jurnal Penyesuai'!$S$4:$S$21) -> 0 | Y72: =SUMIF('Jurnal Penyesuai'!$R$4:$R$21,AA67,'Jurnal Penyesuai'!$T$4:$T$21) -> 0 | Z72: =Z71+X72-Y72 -> 9800000 | AA72: =IF(Z71="",AA71+Y72-X72,"")
B75: Account: | E75: GENERAL LEDGER | I75: Account Number: | K75: Account: | N75: GENERAL LEDGER | R75: Account Number: | T75: Account: | W75: GENERAL LEDGER | AA75: Account Number:
B76: Aktiva Tetap | I76: {=xLOOKUP(B76,'balance sheet'!$C$5:$C$38,'balance sheet'!$B$5:$B$38)} -> 108 | K76: Pembelian | R76: {=xLOOKUP(K76,'balance sheet'!$C$5:$C$38,'balance sheet'!$B$5:$B$38)} -> 500 | T76: Beban Air, Listrik dan Telepon | AA76: {=xLOOKUP(T76,'balance sheet'!$C$5:$C$38,'balance sheet'!$B$5:$B$38)} -> 608
B77: Date | D77: Description | E77: Ref. | F77: Debet | G77: Credit | H77: Balance | K77: Date | M77: Description | N77: Ref. | O77: Debet | P77: Credit | Q77: Balance | T77: Date | V77: Description | W77: Ref. | X77: Debet | Y77: Credit | Z77: Balance
H78: Debet | I78: Credit | Q78: Debet | R78: Credit | Z78: Debet | AA78: Credit
B79: Dec | C79: 1 | D79: Opening Balance | H79: {=XLOOKUP(I76,'balance sheet'!B:B,'balance sheet'!D:D)} -> 3424000000 | K79: Dec | L79: 1 | M79: Opening Balance | Q79: {=XLOOKUP(R76,'balance sheet'!$B:$B,'balance sheet'!$D:$E)} -> 2857000000 | T79: Dec | U79: 1 | V79: Opening Balance | Z79: =VLOOKUP(AA76,'balance sheet'!B:E,4)
C80: 31 | E80: JU | F80: =SUMIF('Jurnal Umum'!$C$119:$C$130,I76,'Jurnal Umum'!$D$119:$D$130) -> 0 | G80: =SUMIF('Jurnal Umum'!$C$119:$C$130,I76,'Jurnal Umum'!$E$119:$E$130) -> 0 | H80: =H79+F80-G80 -> 3424000000 | I80: =IF(I79+G80-F80<0,"",I79+G80-F80) -> 0 | L80: 31 | N80: JU | O80: =SUMIF('Jurnal Umum'!$C$119:$C$130,R76,'Jurnal Umum'!$D$119:$D$130) -> 431200 | P80: =SUMIF('Jurnal Umum'!$C$119:$C$130,R76,'Jurnal Umum'!$E$119:$E$130) -> 0 | Q80: =Q79+O80-P80 -> 2857431200 | R80: =IF(and(Q79="",O79="",P79=""),"",IF(R79+P80-O80<0,"","")) | U80: 31 | W80: JU | X80: =SUMIF('Jurnal Umum'!$C$119:$C$130,AA76,'Jurnal Umum'!$D$119:$D$130) -> 450000 | Y80: =SUMIF('Jurnal Umum'!$C$119:$C$130,AA76,'Jurnal Umum'!$E$119:$E$130) -> 0 | Z80: =Z79+X80-Y80 -> 450000 | AA80: =IF(and(Z79="",X79="",Y79=""),"",AA79+Y80-X80)
C81: 31 | E81: JP | F81: =SUMIF('Jurnal Penyesuai'!$R$4:$R$21,I76,'Jurnal Penyesuai'!$S$4:$S$21) -> 0 | G81: =SUMIF('Jurnal Penyesuai'!$R$4:$R$21,I76,'Jurnal Penyesuai'!$T$4:$T$21) -> 0 | H81: =H80+F81-G81 -> 3424000000 | I81: =IF(H80="",I80+G81-F81,"") | L81: 31 | N81: JP | O81: =SUMIF('Jurnal Penyesuai'!$R$4:$R$21,R76,'Jurnal Penyesuai'!$S$4:$S$21) -> 0 | P81: =SUMIF('Jurnal Penyesuai'!$R$4:$R$21,R76,'Jurnal Penyesuai'!$T$4:$T$21) -> 0 | Q81: =Q80+O81-P81 -> 2857431200 | R81: =IF(Q80="",R80+P81-O81,"") | U81: 31 | W81: JP | X81: =SUMIF('Jurnal Penyesuai'!$R$4:$R$21,AA76,'Jurnal Penyesuai'!$S$4:$S$21) -> 0 | Y81: =SUMIF('Jurnal Penyesuai'!$R$4:$R$21,AA76,'Jurnal Penyesuai'!$T$4:$T$21) -> 0 | Z81: =Z80+X81-Y81 -> 450000 | AA81: =IF(Z80="",AA80+Y81-X81,"")
B84: Account: | E84: GENERAL LEDGER | I84: Account Number: | K84: Account: | N84: GENERAL LEDGER | R84: Account Number: | T84: Account: | W84: GENERAL LEDGER | AA84: Account Number:
B85: Akumulasi Penyusutan Aktiva Tetap | I85: {=xLOOKUP(B85,'balance sheet'!$C$5:$C$38,'balance sheet'!$B$5:$B$38)} -> 109 | K85: Retur Pembelian | R85: {=xLOOKUP(K85,'balance sheet'!$C$5:$C$38,'balance sheet'!$B$5:$B$38)} -> 501 | T85: Pendapatan Bunga | AA85: {=xLOOKUP(T85,'balance sheet'!$C$5:$C$38,'balance sheet'!$B$5:$B$38)} -> 700
B86: Date | D86: Description | E86: Ref. | F86: Debet | G86: Credit | H86: Balance | K86: Date | M86: Description | N86: Ref. | O86: Debet | P86: Credit | Q86: Balance | T86: Date | V86: Description | W86: Ref. | X86: Debet | Y86: Credit | Z86: Balance
H87: Debet | I87: Credit | Q87: Debet | R87: Credit | Z87: Debet | AA87: Credit
B88: Dec | C88: 1 | D88: Opening Balance | H88: {=XLOOKUP(I85,'balance sheet'!B:B,'balance sheet'!D:E)} | I88: 1064400000 | K88: Dec | L88: 1 | M88: Opening Balance | Q88: {=XLOOKUP(R85,'balance sheet'!$B:$B,'balance sheet'!$D:$E)} | R88: 7000000 | T88: Dec | U88: 1 | V88: Opening Balance | Z88: =VLOOKUP(AA85,'balance sheet'!B:E,4) -> 15000000
C89: 31 | E89: JU | F89: =SUMIF('Jurnal Umum'!$C$119:$C$130,I85,'Jurnal Umum'!$D$119:$D$130) -> 0 | G89: =SUMIF('Jurnal Umum'!$C$119:$C$130,I85,'Jurnal Umum'!$E$119:$E$130) -> 0 | H89: =H88+F89-G89 -> 0 | I89: =IF(I88+G89-F89<0,"",I88+G89-F89) -> 1064400000 | L89: 31 | N89: JU | O89: =SUMIF('Jurnal Umum'!$C$119:$C$130,R85,'Jurnal Umum'!$D$119:$D$130) -> 0 | P89: =SUMIF('Jurnal Umum'!$C$119:$C$130,R85,'Jurnal Umum'!$E$119:$E$130) -> 0 | Q89: =Q88+O89-P89 -> 0 | R89: =IF(and(Q88="",O88="",P88=""),"",IF(R88+P89-O89<0,"","")) | U89: 31 | W89: JU | X89: =SUMIF('Jurnal Umum'!$C$119:$C$130,AA85,'Jurnal Umum'!$D$119:$D$130) -> 0 | Y89: =SUMIF('Jurnal Umum'!$C$119:$C$130,AA85,'Jurnal Umum'!$E$119:$E$130) -> 0 | Z89: =Z88+X89-Y89 -> 15000000 | AA89: =IF(and(Z88="",X88="",Y88=""),"",AA88+Y89-X89) -> 0
C90: 31 | E90: JP | F90: =SUMIF('Jurnal Penyesuai'!$R$4:$R$21,I85,'Jurnal Penyesuai'!$S$4:$S$21) -> 0 | G90: =SUMIF('Jurnal Penyesuai'!$R$4:$R$21,I85,'Jurnal Penyesuai'!$T$4:$T$21) -> 336600000 | H90: =H89+F90-G90 -> -336600000 | I90: =IF(H89="",I89+G90-F90,"") | L90: 31 | N90: JP | O90: =SUMIF('Jurnal Penyesuai'!$R$4:$R$21,R85,'Jurnal Penyesuai'!$S$4:$S$21) -> 0 | P90: =SUMIF('Jurnal Penyesuai'!$R$4:$R$21,R85,'Jurnal Penyesuai'!$T$4:$T$21) -> 0 | Q90: =Q89+O90-P90 -> 0 | R90: =IF(Q89="",R89+P90-O90,"") | U90: 31 | W90: JP | X90: =SUMIF('Jurnal Penyesuai'!$R$4:$R$21,AA85,'Jurnal Penyesuai'!$S$4:$S$21) -> 0 | Y90: =SUMIF('Jurnal Penyesuai'!$R$4:$R$21,AA85,'Jurnal Penyesuai'!$T$4:$T$21) -> 2000000 | Z90: =Z89+X90-Y90 -> 13000000 | AA90: =IF(Z89="",AA89+Y90-X90,"")
AA92: `

Sheet Jurnal Penyesuai
C2: PT. GUNUNG SEMERU | K2: PT. GUNUNG SEMERU | R2: Recapitulation
R3: No. Akun | S3: Debet | T3: Kredit
F4: No: 01/BAP/GS/IV/2019 | N4: No: 05/BAP/GS/IV/2019 | R4: 100 | S4: =SUMIF($C:$C,$R4,F:F)+SUMIF($K:$K,$R4,N:N) -> 990000 | T4: =SUMIF($C:$C,$R4,G:G)+SUMIF($K:$K,$R4,O:O) -> 0
C5: Tanggal : | D5: 43585 | K5: Tanggal : | L5: 43585 | R5: 103 | S5: =SUMIF($C:$C,R5,F:F)+SUMIF($K:$K,R5,N:N) -> 20300000 | T5: =SUMIF($C:$C,$R5,G:G)+SUMIF($K:$K,$R5,O:O) -> 22450000
C6: Transaksi : | D6: SISA PERLENGKAPAN | K6: Transaksi : | L6: Pembayaran Iklan | R6: 104 | S6: =SUMIF($C:$C,R6,F:F)+SUMIF($K:$K,R6,N:N) -> 0 | T6: =SUMIF($C:$C,$R6,G:G)+SUMIF($K:$K,$R6,O:O) -> 1300000
R7: 105 | S7: =SUMIF($C:$C,R7,F:F)+SUMIF($K:$K,R7,N:N) -> 0 | T7: =SUMIF($C:$C,$R7,G:G)+SUMIF($K:$K,$R7,O:O) -> 500000
R8: 106 | S8: =SUMIF($C:$C,R8,F:F)+SUMIF($K:$K,R8,N:N) -> 0 | T8: =SUMIF($C:$C,$R8,G:G)+SUMIF($K:$K,$R8,O:O) -> 400000
C9: No. Akun | D9: Nama Akun | F9: Debet | G9: Kredit | K9: No. Akun | L9: Nama Akun | N9: Debet | O9: Kredit | R9: 107 | S9: =SUMIF($C:$C,R9,F:F)+SUMIF($K:$K,R9,N:N) -> 0 | T9: =SUMIF($C:$C,$R9,G:G)+SUMIF($K:$K,$R9,O:O) -> 25000
C10: {=IFERROR(IF(D10<>"",XLOOKUP(D10,'balance sheet'!$C$5:$C$38,'balance sheet'!$B$5:$B$38),XLOOKUP(E10,'balance sheet'!$C$5:$C$38,'balance sheet'!$B$5:$B$38)),"")} -> 600 | D10: Beban Perlengkapan Kantor | F10: =60%*1300000 -> 780000 | K10: {=IFERROR(IF(L10<>"",XLOOKUP(L10,'balance sheet'!$C$5:$C$38,'balance sheet'!$B$5:$B$38),XLOOKUP(M10,'balance sheet'!$C$5:$C$38,'balance sheet'!$B$5:$B$38)),"")} -> 603 | L10: Beban Iklan | N10: 400000 | R10: 201 | S10: =SUMIF($C:$C,R10,F:F)+SUMIF($K:$K,R10,N:N) -> 0 | T10: =SUMIF($C:$C,$R10,G:G)+SUMIF($K:$K,$R10,O:O) -> 80000
C11: {=IFERROR(IF(D11<>"",XLOOKUP(D11,'balance sheet'!$C$5:$C$38,'balance sheet'!$B$5:$B$38),XLOOKUP(E11,'balance sheet'!$C$5:$C$38,'balance sheet'!$B$5:$B$38)),"")} -> 601 | D11: Beban Perlengkapan Toko | F11: =1300000-F10 -> 520000 | K11: {=IFERROR(IF(L11<>"",XLOOKUP(L11,'balance sheet'!$C$5:$C$38,'balance sheet'!$B$5:$B$38),XLOOKUP(M11,'balance sheet'!$C$5:$C$38,'balance sheet'!$B$5:$B$38)),"")} -> 106 | M11: Iklan Dibayar Dimuka | O11: 400000 | R11: 303 | S11: =SUMIF($C:$C,R11,F:F)+SUMIF($K:$K,R11,N:N) -> 22450000 | T11: =SUMIF($C:$C,$R11,G:G)+SUMIF($K:$K,$R11,O:O) -> 20300000
C12: {=IFERROR(IF(D12<>"",XLOOKUP(D12,'balance sheet'!$C$5:$C$38,'balance sheet'!$B$5:$B$38),XLOOKUP(E12,'balance sheet'!$C$5:$C$38,'balance sheet'!$B$5:$B$38)),"")} -> 104 | E12: Perlengkapan | G12: =1300000 -> 1300000 | K12: {=IFERROR(IF(L12<>"",XLOOKUP(L12,'balance sheet'!$C$5:$C$38,'balance sheet'!$B$5:$B$38),XLOOKUP(M12,'balance sheet'!$C$5:$C$38,'balance sheet'!$B$5:$B$38)),"")} | R12: 600 | S12: =SUMIF($C:$C,R12,F:F)+SUMIF($K:$K,R12,N:N) -> 780000 | T12: =SUMIF($C:$C,$R12,G:G)+SUMIF($K:$K,$R12,O:O) -> 0
C13: {=IFERROR(IF(D13<>"",XLOOKUP(D13,'balance sheet'!$C$5:$C$38,'balance sheet'!$B$5:$B$38),XLOOKUP(E13,'balance sheet'!$C$5:$C$38,'balance sheet'!$B$5:$B$38)),"")} | K13: {=IFERROR(IF(L13<>"",XLOOKUP(L13,'balance sheet'!$C$5:$C$38,'balance sheet'!$B$5:$B$38),XLOOKUP(M13,'balance sheet'!$C$5:$C$38,'balance sheet'!$B$5:$B$38)),"")} | R13: 601 | S13: =SUMIF($C:$C,R13,F:F)+SUMIF($K:$K,R13,N:N) -> 520000 | T13: =SUMIF($C:$C,$R13,G:G)+SUMIF($K:$K,$R13,O:O) -> 0
R14: 602 | S14: =SUMIF($C:$C,R14,F:F)+SUMIF($K:$K,R14,N:N) -> 500000 | T14: =SUMIF($C:$C,$R14,G:G)+SUMIF($K:$K,$R14,O:O) -> 0
C15: Diperiksa oleh : | E15: Diposting oleh : | G15: Dibuat oleh : | K15: Diperiksa oleh : | M15: Diposting oleh : | O15: Dibuat oleh : | R15: 603 | S15: =SUMIF($C:$C,R15,F:F)+SUMIF($K:$K,R15,N:N) -> 400000 | T15: =SUMIF($C:$C,$R15,G:G)+SUMIF($K:$K,$R15,O:O) -> 0
R16: 604 | S16: =SUMIF($C:$C,R16,F:F)+SUMIF($K:$K,R16,N:N) -> 25000 | T16: =SUMIF($C:$C,$R16,G:G)+SUMIF($K:$K,$R16,O:O) -> 0
R17: 605 | S17: =SUMIF($C:$C,R17,F:F)+SUMIF($K:$K,R17,N:N) -> 336600000 | T17: =SUMIF($C:$C,$R17,G:G)+SUMIF($K:$K,$R17,O:O) -> 0
R18: 109 | S18: =SUMIF($C:$C,R18,F:F)+SUMIF($K:$K,R18,N:N) -> 0 | T18: =SUMIF($C:$C,$R18,G:G)+SUMIF($K:$K,$R18,O:O) -> 336600000
R19: 609 | S19: =SUMIF($C:$C,R19,F:F)+SUMIF($K:$K,R19,N:N) -> 1010000 | T19: =SUMIF($C:$C,$R19,G:G)+SUMIF($K:$K,$R19,O:O) -> 0
R20: 610 | S20: =SUMIF($C:$C,R20,F:F)+SUMIF($K:$K,R20,N:N) -> 80000 | T20: =SUMIF($C:$C,$R20,G:G)+SUMIF($K:$K,$R20,O:O) -> 0
R21: 700 | S21: =SUMIF($C:$C,R21,F:F)+SUMIF($K:$K,R21,N:N) -> 0 | T21: =SUMIF($C:$C,$R21,G:G)+SUMIF($K:$K,$R21,O:O) -> 2000000
S22: =SUM(S4:S21) -> 383655000 | T22: =SUM(T4:T21) -> 383655000
C25: PT. GUNUNG SEMERU | K25: PT. GUNUNG SEMERU
F27: No: 02/BAP/GS/IV/2019 | N27: No: 06/BAP/GS/IV/2019
C28: Tanggal : | D28: 43585 | K28: Tanggal : | L28: 43585
C29: Transaksi : | D29: SISA PERSEDIAAN | K29: Transaksi : | L29: Pendapatan Bunga
C32: No. Akun | D32: Nama Akun | F32: Debet | G32: Kredit | K32: No. Akun | L32: Nama Akun | N32: Debet | O32: Kredit
C33: {=IFERROR(IF(D33<>"",XLOOKUP(D33,'balance sheet'!$C$5:$C$38,'balance sheet'!$B$5:$B$38),XLOOKUP(E33,'balance sheet'!$C$5:$C$38,'balance sheet'!$B$5:$B$38)),"")} -> 103 | D33: Persediaan Barang Dagang | F33: 20300000 | K33: {=IFERROR(IF(L33<>"",XLOOKUP(L33,'balance sheet'!$C$5:$C$38,'balance sheet'!$B$5:$B$38),XLOOKUP(M33,'balance sheet'!$C$5:$C$38,'balance sheet'!$B$5:$B$38)),"")} -> 100 | L33: Kas Di Bank | N33: 990000
C34: {=IFERROR(IF(D34<>"",XLOOKUP(D34,'balance sheet'!$C$5:$C$38,'balance sheet'!$B$5:$B$38),XLOOKUP(E34,'balance sheet'!$C$5:$C$38,'balance sheet'!$B$5:$B$38)),"")} -> 303 | E34: Ikhtisar Laba Rugi | G34: 20300000 | K34: {=IFERROR(IF(L34<>"",XLOOKUP(L34,'balance sheet'!$C$5:$C$38,'balance sheet'!$B$5:$B$38),XLOOKUP(M34,'balance sheet'!$C$5:$C$38,'balance sheet'!$B$5:$B$38)),"")} -> 609 | L34: Beban Administrasi Bank | N34: 1010000
C35: {=IFERROR(IF(D35<>"",XLOOKUP(D35,'balance sheet'!$C$5:$C$38,'balance sheet'!$B$5:$B$38),XLOOKUP(E35,'balance sheet'!$C$5:$C$38,'balance sheet'!$B$5:$B$38)),"")} -> 303 | D35: Ikhtisar Laba Rugi | F35: 22450000 | K35: {=IFERROR(IF(L35<>"",XLOOKUP(L35,'balance sheet'!$C$5:$C$38,'balance sheet'!$B$5:$B$38),XLOOKUP(M35,'balance sheet'!$C$5:$C$38,'balance sheet'!$B$5:$B$38)),"")} -> 700 | M35: Pendapatan Bunga | O35: 2000000
C36: {=IFERROR(IF(D36<>"",XLOOKUP(D36,'balance sheet'!$C$5:$C$38,'balance sheet'!$B$5:$B$38),XLOOKUP(E36,'balance sheet'!$C$5:$C$38,'balance sheet'!$B$5:$B$38)),"")} -> 103 | E36: Persediaan Barang Dagang | G36: 22450000 | K36: {=IFERROR(IF(L36<>"",XLOOKUP(L36,'balance sheet'!$C$5:$C$38,'balance sheet'!$B$5:$B$38),XLOOKUP(M36,'balance sheet'!$C$5:$C$38,'balance sheet'!$B$5:$B$38)),"")}
C38: Diperiksa oleh : | E38: Diposting oleh : | G38: Dibuat oleh : | K38: Diperiksa oleh : | M38: Diposting oleh : | O38: Dibuat oleh :
C43: PT. GUNUNG SEMERU | K43: PT. GUNUNG SEMERU
F45: No: 03/BAP/GS/IV/2019 | N45: No: 07/BAP/GS/IV/2019
C46: Tanggal : | D46: 43585 | K46: Tanggal : | L46: 43585
C47: Transaksi : | D47: Sewa Gudang | K47: Transaksi : | L47: PPH 21
C50: No. Akun | D50: Nama Akun | F50: Debet | G50: Kredit | K50: No. Akun | L50: Nama Akun | N50: Debet | O50: Kredit
C51: {=IFERROR(IF(D51<>"",XLOOKUP(D51,'balance sheet'!$C$5:$C$38,'balance sheet'!$B$5:$B$38),XLOOKUP(E51,'balance sheet'!$C$5:$C$38,'balance sheet'!$B$5:$B$38)),"")} -> 602 | D51: Beban Sewa | F51: 500000 | K51: {=IFERROR(IF(L51<>"",XLOOKUP(L51,'balance sheet'!$C$5:$C$38,'balance sheet'!$B$5:$B$38),XLOOKUP(M51,'balance sheet'!$C$5:$C$38,'balance sheet'!$B$5:$B$38)),"")} -> 610 | L51: Beban PPH 21 | N51: 80000
C52: {=IFERROR(IF(D52<>"",XLOOKUP(D52,'balance sheet'!$C$5:$C$38,'balance sheet'!$B$5:$B$38),XLOOKUP(E52,'balance sheet'!$C$5:$C$38,'balance sheet'!$B$5:$B$38)),"")} -> 105 | E52: Sewa Gudang Dibayar Dimuka | G52: 500000 | K52: {=IFERROR(IF(L52<>"",XLOOKUP(L52,'balance sheet'!$C$5:$C$38,'balance sheet'!$B$5:$B$38),XLOOKUP(M52,'balance sheet'!$C$5:$C$38,'balance sheet'!$B$5:$B$38)),"")} -> 201 | M52: Utang PPH 21 | O52: 80000
C54: {=IFERROR(IF(D54<>"",XLOOKUP(D54,'balance sheet'!$C$5:$C$38,'balance sheet'!$B$5:$B$38),XLOOKUP(E54,'balance sheet'!$C$5:$C$38,'balance sheet'!$B$5:$B$38)),"")} | K54: {=IFERROR(IF(L54<>"",XLOOKUP(L54,'balance sheet'!$C$5:$C$38,'balance sheet'!$B$5:$B$38),XLOOKUP(M54,'balance sheet'!$C$5:$C$38,'balance sheet'!$B$5:$B$38)),"")}
C56: Diperiksa oleh : | E56: Diposting oleh : | G56: Dibuat oleh : | K56: Diperiksa oleh : | M56: Diposting oleh : | O56: Dibuat oleh :
C61: PT. GUNUNG SEMERU | K61: PT. GUNUNG SEMERU
F63: No: 04/BAP/GS/IV/2019 | N63: No: 08/BAP/GS/IV/2019
C64: Tanggal : | D64: 43585 | K64: Tanggal : | L64: 43585
C65: Transaksi : | D65: Asuransi | K65: Transaksi : | L65: Penyusutan Aktiva Tetap
C68: No. Akun | D68: Nama Akun | F68: Debet | G68: Kredit | K68: No. Akun | L68: Nama Akun | N68: Debet | O68: Kredit
C69: {=IFERROR(IF(D69<>"",XLOOKUP(D69,'balance sheet'!$C$5:$C$38,'balance sheet'!$B$5:$B$38),XLOOKUP(E69,'balance sheet'!$C$5:$C$38,'balance sheet'!$B$5:$B$38)),"")} -> 604 | D69: Beban Asuransi | F69: 25000 | K69: {=IFERROR(IF(L69<>"",XLOOKUP(L69,'balance sheet'!$C$5:$C$38,'balance sheet'!$B$5:$B$38),XLOOKUP(M69,'balance sheet'!$C$5:$C$38,'balance sheet'!$B$5:$B$38)),"")} -> 605 | L69: Beban Penyusutan Aktiva Tetap | N69: 336600000
C70: {=IFERROR(IF(D70<>"",XLOOKUP(D70,'balance sheet'!$C$5:$C$38,'balance sheet'!$B$5:$B$38),XLOOKUP(E70,'balance sheet'!$C$5:$C$38,'balance sheet'!$B$5:$B$38)),"")} -> 107 | E70: Asuransi Dibayar Dimuka | G70: 25000 | K70: {=IFERROR(IF(L70<>"",XLOOKUP(L70,'balance sheet'!$C$5:$C$38,'balance sheet'!$B$5:$B$38),XLOOKUP(M70,'balance sheet'!$C$5:$C$38,'balance sheet'!$B$5:$B$38)),"")} -> 109 | M70: Akumulasi Penyusutan Aktiva Tetap | O70: 336600000
C71: {=IFERROR(IF(D71<>"",XLOOKUP(D71,'balance sheet'!$C$5:$C$38,'balance sheet'!$B$5:$B$38),XLOOKUP(E71,'balance sheet'!$C$5:$C$38,'balance sheet'!$B$5:$B$38)),"")}
C72: {=IFERROR(IF(D72<>"",XLOOKUP(D72,'balance sheet'!$C$5:$C$38,'balance sheet'!$B$5:$B$38),XLOOKUP(E72,'balance sheet'!$C$5:$C$38,'balance sheet'!$B$5:$B$38)),"")} | K72: {=IFERROR(IF(L72<>"",XLOOKUP(L72,'balance sheet'!$C$5:$C$38,'balance sheet'!$B$5:$B$38),XLOOKUP(M72,'balance sheet'!$C$5:$C$38,'balance sheet'!$B$5:$B$38)),"")}
C74: Diperiksa oleh : | E74: Diposting oleh : | G74: Dibuat oleh : | K74: Diperiksa oleh : | M74: Diposting oleh : | O74: Dibuat oleh :

Sheet NERACA penyesuai
A2: PT GUNUNG SEMERU
A4: PERKIRAAN BUKU BESAR | C4: DEBET | D4: KREDIT
A5: 100 | B5: Kas Di Bank | C5: =Lajur!K5 -> 136000000 | D5: =Lajur!L5
A6: 101 | B6: Kas Kecil | C6: =Lajur!K6 -> 3170000 | D6: =Lajur!L6
A7: 102 | B7: Piutang Dagang | C7: =Lajur!K7 -> 2640000 | D7: =Lajur!L7
A8: 103 | B8: Persediaan Barang Dagang | C8: =Lajur!K8 -> 20850000 | D8: =Lajur!L8
A9: 104 | B9: Perlengkapan | C9: =Lajur!K9 -> 700000 | D9: =Lajur!L9
A10: 105 | B10: Sewa Gudang Dibayar Dimuka | C10: =Lajur!K10 -> 0 | D10: =Lajur!L10
A11: 106 | B11: Iklan Dibayar Dimuka | C11: =Lajur!K11 -> 100000 | D11: =Lajur!L11
A12: 107 | B12: Asuransi Dibayar Dimuka | C12: =Lajur!K12 -> 275000 | D12: =Lajur!L12
A13: 108 | B13: Aktiva Tetap | C13: =Lajur!K13 -> 3424000000 | D13: =Lajur!L13
A14: 109 | B14: Akumulasi Penyusutan Aktiva Tetap | C14: =Lajur!K14 | D14: =Lajur!L14 -> 1401000000
A15: 200 | B15: Utang Dagang | C15: =Lajur!K15 -> 0 | D15: =Lajur!L15 -> 431200
A16: 201 | B16: Utang PPH 21 | C16: =Lajur!K16 | D16: =Lajur!L16 -> 80000
... A38: 700 | B38: Pendapatan Bunga | C38: =Lajur!K38 | D38: =Lajur!L38 -> 17000000
C39: =SUM(C5:C38) -> 7269981200 | D39: =SUM(D5:D38) -> 7269981200

Sheet Lajur
C1: WORKSHEET
C2: December 31, 2011
A3: Acc. No. | B3: Description | C3: Trial Balance | E3: Journal | G3: Balance Sheet | I3: Adjusting Journal Entries | K3: Adjusted Trial Balance | M3: Income Summary | O3: EQUITY CHANGE | Q3: Balance Sheet
C4: DEBET | D4: CREDIT | E4: DEBET | F4: CREDIT | G4: DEBET | H4: CREDIT | I4: DEBET | J4: CREDIT | K4: DEBET | L4: CREDIT | M4: DEBET | N4: CREDIT | O4: DEBET | P4: CREDIT | Q4: DEBET | R4: CREDIT
A5: {='balance sheet'!B5:E38} -> 100 | B5: Kas Di Bank | C5: 125000000 | E5: {=IFERROR(XLOOKUP(A5,'Jurnal Umum'!$C$119:$C$129,'Jurnal Umum'!$D$119:$E$129),"")} -> 11550000 | F5: 1540000 | G5: =IF(D5="",IF(C5+E5-F5<0,"",C5+E5-F5),"") -> 135010000 | H5: =IF(C5="",IF(D5-E5+F5<0,"",D5-E5+F5),"") | I5: {=IFERROR(XLOOKUP(A5,'Jurnal Penyesuai'!$R$4:$R$21,'Jurnal Penyesuai'!$S$4:$T$21),"")} -> 990000 | J5: 0 | K5: =IF(G5+I5-J5<0,"",G5+I5-J5) -> 136000000 | L5: =IF(H5-I5+J5<0,"",IF((H5-I5+J5)-(G5+I5-J5)<0,"",(H5-I5+J5)-(G5+I5-J5))) | Q5: =IF(AND(M5="",O5=""),K5,"") -> 136000000 | R5: =IF(AND(N5="",P5=""),L5,"")
A6: 101 | B6: Kas Kecil | C6: 5000000 | E6: {=IFERROR(XLOOKUP(A6,'Jurnal Umum'!$C$119:$C$129,'Jurnal Umum'!$D$119:$E$129),"")} -> 0 | F6: 1830000 | G6: =IF(D6="",IF(C6+E6-F6<0,"",C6+E6-F6),"") -> 3170000 | H6: =IF(C6="",IF(D6-E6+F6<0,"",D6-E6+F6),"") | I6: {=IFERROR(XLOOKUP(A6,'Jurnal Penyesuai'!$R$4:$R$21,'Jurnal Penyesuai'!$S$4:$T$21),"")} | K6: =IF(G6+I6-J6<0,"",G6+I6-J6) -> 3170000 | L6: =IF(H6-I6+J6<0,"",IF((H6-I6+J6)-(G6+I6-J6)<0,"",(H6-I6+J6)-(G6+I6-J6))) | Q6: =IF(AND(M6="",O6=""),K6,"") -> 3170000 | R6: =IF(AND(N6="",P6=""),L6,"")
A7: 102 | B7: Piutang Dagang | C7: 11550000 | E7: {=IFERROR(XLOOKUP(A7,'Jurnal Umum'!$C$119:$C$129,'Jurnal Umum'!$D$119:$E$129),"")} -> 2640000 | F7: 11550000 | G7: =IF(D7="",IF(C7+E7-F7<0,"",C7+E7-F7),"") -> 2640000 | H7: =IF(C7="",IF(D7-E7+F7<0,"",D7-E7+F7),"") | I7: {=IFERROR(XLOOKUP(A7,'Jurnal Penyesuai'!$R$4:$R$21,'Jurnal Penyesuai'!$S$4:$T$21),"")} | K7: =IF(G7+I7-J7<0,"",G7+I7-J7) -> 2640000 | L7: =IF(H7-I7+J7<0,"",IF((H7-I7+J7)-(G7+I7-J7)<0,"",(H7-I7+J7)-(G7+I7-J7))) | Q7: =IF(AND(M7="",O7=""),K7,"") -> 2640000 | R7: =IF(AND(N7="",P7=""),L7,"")
A8: 103 | B8: Persediaan Barang Dagang | C8: 23000000 | E8: {=IFERROR(XLOOKUP(A8,'Jurnal Umum'!$C$119:$C$129,'Jurnal Umum'!$D$119:$E$129),"")} | G8: =IF(D8="",IF(C8+E8-F8<0,"",C8+E8-F8),"") -> 23000000 | H8: =IF(C8="",IF(D8-E8+F8<0,"",D8-E8+F8),"") | I8: {=IFERROR(XLOOKUP(A8,'Jurnal Penyesuai'!$R$4:$R$21,'Jurnal Penyesuai'!$S$4:$T$21),"")} -> 20300000 | J8: 22450000 | K8: =IF(G8+I8-J8<0,"",G8+I8-J8) -> 20850000 | L8: =IF(H8-I8+J8<0,"",IF((H8-I8+J8)-(G8+I8-J8)<0,"",(H8-I8+J8)-(G8+I8-J8))) | Q8: =IF(AND(M8="",O8=""),K8,"") -> 20850000 | R8: =IF(AND(N8="",P8=""),L8,"")
A9: 104 | B9: Perlengkapan | C9: 2000000 | E9: {=IFERROR(XLOOKUP(A9,'Jurnal Umum'!$C$119:$C$129,'Jurnal Umum'!$D$119:$E$129),"")} | G9: =IF(D9="",IF(C9+E9-F9<0,"",C9+E9-F9),"") -> 2000000 | H9: =IF(C9="",IF(D9-E9+F9<0,"",D9-E9+F9),"") | I9: {=IFERROR(XLOOKUP(A9,'Jurnal Penyesuai'!$R$4:$R$21,'Jurnal Penyesuai'!$S$4:$T$21),"")} -> 0 | J9: 1300000 | K9: =IF(G9+I9-J9<0,"",G9+I9-J9) -> 700000 | L9: =IF(OR(H9-I9+J9>0,K9=""),"",IF((H9-I9+J9)-(G9+I9-J9)<0,"",(H9-I9+J9)-(G9+I9-J9))) | Q9: =IF(AND(M9="",O9=""),K9,"") -> 700000 | R9: =IF(AND(N9="",P9=""),L9,"")
A10: 105 | B10: Sewa Gudang Dibayar Dimuka | E10: {=IFERROR(XLOOKUP(A10,'Jurnal Umum'!$C$119:$C$129,'Jurnal Umum'!$D$119:$E$129),"")} -> 500000 | F10: 0 | G10: =IF(D10="",IF(C10+E10-F10<0,"",C10+E10-F10),"") -> 500000 | H10: =IF(C10="",IF(D10-E10+F10<0,"",D10-E10+F10),"") | I10: {=IFERROR(XLOOKUP(A10,'Jurnal Penyesuai'!$R$4:$R$21,'Jurnal Penyesuai'!$S$4:$T$21),"")} -> 0 | J10: 500000 | K10: =IF(G10+I10-J10<0,"",G10+I10-J10) -> 0 | Q10: =IF(AND(M10="",O10=""),K10,"") -> 0 | R10: =IF(AND(N10="",P10=""),L10,"")
A11: 106 | B11: Iklan Dibayar Dimuka | E11: {=IFERROR(XLOOKUP(A11,'Jurnal Umum'!$C$119:$C$129,'Jurnal Umum'!$D$119:$E$129),"")} -> 500000 | F11: 0 | G11: =IF(D11="",IF(C11+E11-F11<0,"",C11+E11-F11),"") -> 500000 | H11: =IF(C11="",IF(D11-E11+F11<0,"",D11-E11+F11),"") | I11: {=IFERROR(XLOOKUP(A11,'Jurnal Penyesuai'!$R$4:$R$21,'Jurnal Penyesuai'!$S$4:$T$21),"")} -> 0 | J11: 400000 | K11: =IF(G11+I11-J11<0,"",G11+I11-J11) -> 100000 | Q11: =IF(AND(M11="",O11=""),K11,"") -> 100000 | R11: =IF(AND(N11="",P11=""),L11,"")
A12: 107 | B12: Asuransi Dibayar Dimuka | E12: {=IFERROR(XLOOKUP(A12,'Jurnal Umum'!$C$119:$C$129,'Jurnal Umum'!$D$119:$E$129),"")} -> 300000 | F12: 0 | G12: =IF(D12="",IF(C12+E12-F12<0,"",C12+E12-F12),"") -> 300000 | H12: =IF(C12="",IF(D12-E12+F12<0,"",D12-E12+F12),"") | I12: {=IFERROR(XLOOKUP(A12,'Jurnal Penyesuai'!$R$4:$R$21,'Jurnal Penyesuai'!$S$4:$T$21),"")} -> 0 | J12: 25000 | K12: =IF(G12+I12-J12<0,"",G12+I12-J12) -> 275000 | L12: =IF(H12-I12+J12<0,"",IF((H12-I12+J12)-(G12+I12-J12)<0,"",(H12-I12+J12)-(G12+I12-J12))) | Q12: =IF(AND(M12="",O12=""),K12,"") -> 275000 | R12: =IF(AND(N12="",P12=""),L12,"")
A13: 108 | B13: Aktiva Tetap | C13: 3424000000 | E13: {=IFERROR(XLOOKUP(A13,'Jurnal Umum'!$C$119:$C$129,'Jurnal Umum'!$D$119:$E$129),"")} | G13: =IF(D13="",IF(C13+E13-F13<0,"",C13+E13-F13),"") -> 3424000000 | H13: =IF(C13="",IF(D13-E13+F13<0,"",D13-E13+F13),"") | I13: {=IFERROR(XLOOKUP(A13,'Jurnal Penyesuai'!$R$4:$R$21,'Jurnal Penyesuai'!$S$4:$T$21),"")} | K13: =IF(G13+I13-J13<0,"",G13+I13-J13) -> 3424000000 | L13: =IF(H13-I13+J13<0,"",IF((H13-I13+J13)-(G13+I13-J13)<0,"",(H13-I13+J13)-(G13+I13-J13))) | Q13: =IF(AND(M13="",O13=""),K13,"") -> 3424000000 | R13: =IF(AND(N13="",P13=""),L13,"")
A14: 109 | B14: Akumulasi Penyusutan Aktiva Tetap | D14: 1064400000 | E14: {=IFERROR(XLOOKUP(A14,'Jurnal Umum'!$C$119:$C$129,'Jurnal Umum'!$D$119:$E$129),"")} | G14: =IF(D14="",IF(C14+E14-F14<0,"",C14+E14-F14),"") | H14: =IF(C14="",IF(D14-E14+F14<0,"",D14-E14+F14),"") -> 1064400000 | I14: {=IFERROR(XLOOKUP(A14,'Jurnal Penyesuai'!$R$4:$R$21,'Jurnal Penyesuai'!$S$4:$T$21),"")} -> 0 | J14: 336600000 | K14: =IF(G14+I14-J14<0,"",G14+I14-J14) | L14: =H14+J14 -> 1401000000 | Q14: =IF(AND(M14="",O14=""),K14,"") | R14: =IF(AND(N14="",P14=""),L14,"") -> 1401000000
A15: 200 | B15: Utang Dagang | D15: 1540000 | E15: {=IFERROR(XLOOKUP(A15,'Jurnal Umum'!$C$119:$C$129,'Jurnal Umum'!$D$119:$E$129),"")} -> 1540000 | F15: 431200 | G15: =IF(D15="",IF(C15+E15-F15<0,"",C15+E15-F15),"") | H15: =IF(C15="",IF(D15-E15+F15<0,"",D15-E15+F15),"") -> 431200 | I15: {=IFERROR(XLOOKUP(A15,'Jurnal Penyesuai'!$R$4:$R$21,'Jurnal Penyesuai'!$S$4:$T$21),"")} | K15: =IF(G15+I15-J15<0,"",G15+I15-J15) -> 0 | L15: =IF(H15-I15+J15<0,"",IF((H15-I15+J15)-(G15+I15-J15)<0,"",(H15-I15+J15)-(G15+I15-J15))) -> 431200 | Q15: =IF(AND(M15="",O15=""),K15,"") -> 0 | R15: =IF(AND(N15="",P15=""),L15,"") -> 431200
A16: 201 | B16: Utang PPH 21 | D16: 80000 | E16: {=IFERROR(XLOOKUP(A16,'Jurnal Umum'!$C$119:$C$129,'Jurnal Umum'!$D$119:$E$129),"")} -> 80000 | F16: 0 | G16: =IF(D16="",IF(C16+E16-F16<0,"",C16+E16-F16),"") | H16: =IF(C16="",IF(D16-E16+F16<0,"",D16-E16+F16),"") -> 0 | I16: {=IFERROR(XLOOKUP(A16,'Jurnal Penyesuai'!$R$4:$R$21,'Jurnal Penyesuai'!$S$4:$T$21),"")} -> 0 | J16: 80000 | K16: =IF(G16+I16-J16<0,"",G16+I16-J16) | L16: =J16 -> 80000 | Q16: =IF(AND(M16="",O16=""),K16,"") | R16: =IF(AND(N16="",P16=""),L16,"") -> 80000
A17: 202 | B17: Utang Gaji | E17: {=IFERROR(XLOOKUP(A17,'Jurnal Umum'!$C$119:$C$129,'Jurnal Umum'!$D$119:$E$129),"")} | G17: =IF(D17="",IF(C17+E17-F17<0,"",C17+E17-F17),"") -> 0 | H17: =IF(C17="",IF(D17-E17+F17<0,"",D17-E17+F17),"") -> 0 | I17: {=IFERROR(XLOOKUP(A17,'Jurnal Penyesuai'!$R$4:$R$21,'Jurnal Penyesuai'!$S$4:$T$21),"")} | K17: =IF(G17+I17-J17<0,"",G17+I17-J17) -> 0 | L17: =IF(H17-I17+J17<0,"",IF((H17-I17+J17)-(G17+I17-J17)<0,"",(H17-I17+J17)-(G17+I17-J17))) -> 0 | Q17: =IF(AND(M17="",O17=""),K17,"") -> 0 | R17: =IF(AND(N17="",P17=""),L17,"") -> 0
A18: 203 | B18: Utang Air, Listrik, dan Telepon | E18: {=IFERROR(XLOOKUP(A18,'Jurnal Umum'!$C$119:$C$129,'Jurnal Umum'!$D$119:$E$129),"")} | G18: =IF(D18="",IF(C18+E18-F18<0,"",C18+E18-F18),"") -> 0 | H18: =IF(C18="",IF(D18-E18+F18<0,"",D18-E18+F18),"") -> 0 | I18: {=IFERROR(XLOOKUP(A18,'Jurnal Penyesuai'!$R$4:$R$21,'Jurnal Penyesuai'!$S$4:$T$21),"")} | K18: =IF(G18+I18-J18<0,"",G18+I18-J18) -> 0 | L18: =IF(H18-I18+J18<0,"",IF((H18-I18+J18)-(G18+I18-J18)<0,"",(H18-I18+J18)-(G18+I18-J18))) -> 0 | Q18: =IF(AND(M18="",O18=""),K18,"") -> 0 | R18: =IF(AND(N18="",P18=""),L18,"") -> 0
A19: 300 | B19: Modal Saham | D19: 1000000000 | E19: {=IFERROR(XLOOKUP(A19,'Jurnal Umum'!$C$119:$C$129,'Jurnal Umum'!$D$119:$E$129),"")} | G19: =IF(D19="",IF(C19+E19-F19<0,"",C19+E19-F19),"") | H19: =IF(C19="",IF(D19-E19+F19<0,"",D19-E19+F19),"") -> 1000000000 | I19: {=IFERROR(XLOOKUP(A19,'Jurnal Penyesuai'!$R$4:$R$21,'Jurnal Penyesuai'!$S$4:$T$21),"")} | K19: =IF(G19+I19-J19<0,"",G19+I19-J19) -> 0 | L19: =IF(H19-I19+J19<0,"",IF((H19-I19+J19)-(G19+I19-J19)<0,"",(H19-I19+J19)-(G19+I19-J19))) -> 1000000000 | Q19: =IF(AND(M19="",O19=""),K19,"") -> 0 | R19: =IF(AND(N19="",P19=""),L19,"") -> 1000000000
A20: 301 | B20: Agio Saham | D20: 156830000 | E20: {=IFERROR(XLOOKUP(A20,'Jurnal Umum'!$C$119:$C$129,'Jurnal Umum'!$D$119:$E$129),"")} | G20: =IF(D20="",IF(C20+E20-F20<0,"",C20+E20-F20),"") | H20: =IF(C20="",IF(D20-E20+F20<0,"",D20-E20+F20),"") -> 156830000 | I20: {=IFERROR(XLOOKUP(A20,'Jurnal Penyesuai'!$R$4:$R$21,'Jurnal Penyesuai'!$S$4:$T$21),"")} | K20: =IF(G20+I20-J20<0,"",G20+I20-J20) -> 0 | L20: =IF(H20-I20+J20<0,"",IF((H20-I20+J20)-(G20+I20-J20)<0,"",(H20-I20+J20)-(G20+I20-J20))) -> 156830000 | Q20: =IF(AND(M20="",O20=""),K20,"") -> 0 | R20: =IF(AND(N20="",P20=""),L20,"") -> 156830000
A21: 302 | B21: Laba Ditahan | D21: 400000000 | E21: {=IFERROR(XLOOKUP(A21,'Jurnal Umum'!$C$119:$C$129,'Jurnal Umum'!$D$119:$E$129),"")} | G21: =IF(D21="",IF(C21+E21-F21<0,"",C21+E21-F21),"") | H21: =IF(C21="",IF(D21-E21+F21<0,"",D21-E21+F21),"") -> 400000000 | I21: {=IFERROR(XLOOKUP(A21,'Jurnal Penyesuai'!$R$4:$R$21,'Jurnal Penyesuai'!$S$4:$T$21),"")} | K21: =IF(G21+I21-J21<0,"",G21+I21-J21) -> 0 | L21: =IF(H21-I21+J21<0,"",IF((H21-I21+J21)-(G21+I21-J21)<0,"",(H21-I21+J21)-(G21+I21-J21))) -> 400000000 | Q21: =IF(AND(M21="",O21=""),K21,"") -> 0 | R21: =IF(AND(N21="",P21=""),L21,"") -> 400000000
A22: 303 | B22: Ikhtisar Laba Rugi | E22: {=IFERROR(XLOOKUP(A22,'Jurnal Umum'!$C$119:$C$129,'Jurnal Umum'!$D$119:$E$129),"")} | G22: =IF(D22="",IF(C22+E22-F22<0,"",C22+E22-F22),"") -> 0 | H22: =IF(C22="",IF(D22-E22+F22<0,"",D22-E22+F22),"") -> 0 | I22: {=IFERROR(XLOOKUP(A22,'Jurnal Penyesuai'!$R$4:$R$21,'Jurnal Penyesuai'!$S$4:$T$21),"")} -> 22450000 | J22: 20300000 | K22: =IF(G22+I22-J22<0,"",G22+I22-J22) -> 2150000 | L22: =IF(H22-I22+J22<0,"",IF((H22-I22+J22)-(G22+I22-J22)<0,"",(H22-I22+J22)-(G22+I22-J22))) | Q22: =IF(AND(M22="",O22=""),K22,"") -> 2150000 | R22: =IF(AND(N22="",P22=""),L22,"")
A23: 400 | B23: Penjualan | D23: 4285000000 | E23: {=IFERROR(XLOOKUP(A23,'Jurnal Umum'!$C$119:$C$129,'Jurnal Umum'!$D$119:$E$129),"")} -> 0 | F23: 2640000 | G23: =IF(D23="",IF(C23+E23-F23<0,"",C23+E23-F23),"") | H23: =IF(C23="",IF(D23-E23+F23<0,"",D23-E23+F23),"") -> 4287640000 | I23: {=IFERROR(XLOOKUP(A23,'Jurnal Penyesuai'!$R$4:$R$21,'Jurnal Penyesuai'!$S$4:$T$21),"")} | K23: =IF(G23+I23-J23<0,"",G23+I23-J23) -> 0 | L23: =IF(H23-I23+J23<0,"",IF((H23-I23+J23)-(G23+I23-J23)<0,"",(H23-I23+J23)-(G23+I23-J23))) -> 4287640000 | M23: =K23 -> 0 | N23: =L23 -> 4287640000 | Q23: =IF(AND(M23="",O23=""),K23,"") | R23: =IF(AND(N23="",P23=""),L23,"")
A24: 401 | B24: Retur Penjualan | C24: 5000000 | E24: {=IFERROR(XLOOKUP(A24,'Jurnal Umum'!$C$119:$C$129,'Jurnal Umum'!$D$119:$E$129),"")} | G24: =IF(D24="",IF(C24+E24-F24<0,"",C24+E24-F24),"") -> 5000000 | H24: =IF(C24="",IF(D24-E24+F24<0,"",D24-E24+F24),"") | I24: {=IFERROR(XLOOKUP(A24,'Jurnal Penyesuai'!$R$4:$R$21,'Jurnal Penyesuai'!$S$4:$T$21),"")} | K24: =IF(G24+I24-J24<0,"",G24+I24-J24) -> 5000000 | L24: =IF(H24-I24+J24<0,"",IF((H24-I24+J24)-(G24+I24-J24)<0,"",(H24-I24+J24)-(G24+I24-J24))) | M24: =K24 -> 5000000 | N24: =L24 | Q24: =IF(AND(M24="",O24=""),K24,"") | R24: =IF(AND(N24="",P24=""),L24,"")
A25: 500 | B25: Pembelian | C25: 2857000000 | E25: {=IFERROR(XLOOKUP(A25,'Jurnal Umum'!$C$119:$C$129,'Jurnal Umum'!$D$119:$E$129),"")} -> 431200 | F25: 0 | G25: =IF(D25="",IF(C25+E25-F25<0,"",C25+E25-F25),"") -> 2857431200 | H25: =IF(C25="",IF(D25-E25+F25<0,"",D25-E25+F25),"") | I25: {=IFERROR(XLOOKUP(A25,'Jurnal Penyesuai'!$R$4:$R$21,'Jurnal Penyesuai'!$S$4:$T$21),"")} | K25: =IF(G25+I25-J25<0,"",G25+I25-J25) -> 2857431200 | L25: =IF(H25-I25+J25<0,"",IF((H25-I25+J25)-(G25+I25-J25)<0,"",(H25-I25+J25)-(G25+I25-J25))) | M25: =K25 -> 2857431200 | N25: =L25 | Q25: =IF(AND(M25="",O25=""),K25,"") | R25: =IF(AND(N25="",P25=""),L25,"")
A26: 501 | B26: Retur Pembelian | D26: 7000000 | E26: {=IFERROR(XLOOKUP(A26,'Jurnal Umum'!$C$119:$C$129,'Jurnal Umum'!$D$119:$E$129),"")} | G26: =IF(D26="",IF(C26+E26-F26<0,"",C26+E26-F26),"") | H26: =IF(C26="",IF(D26-E26+F26<0,"",D26-E26+F26),"") -> 7000000 | I26: {=IFERROR(XLOOKUP(A26,'Jurnal Penyesuai'!$R$4:$R$21,'Jurnal Penyesuai'!$S$4:$T$21),"")} | K26: =IF(G26+I26-J26<0,"",G26+I26-J26) -> 0 | L26: =IF(H26-I26+J26<0,"",IF((H26-I26+J26)-(G26+I26-J26)<0,"",(H26-I26+J26)-(G26+I26-J26))) -> 7000000 | M26: =K26 -> 0 | N26: =L26 -> 7000000 | Q26: =IF(AND(M26="",O26=""),K26,"") | R26: =IF(AND(N26="",P26=""),L26,"")
A27: 600 | B27: Beban Perlengkapan Kantor | E27: {=IFERROR(XLOOKUP(A27,'Jurnal Umum'!$C$119:$C$129,'Jurnal Umum'!$D$119:$E$129),"")} | G27: =IF(D27="",IF(C27+E27-F27<0,"",C27+E27-F27),"") -> 0 | H27: =IF(C27="",IF(D27-E27+F27<0,"",D27-E27+F27),"") -> 0 | I27: {=IFERROR(XLOOKUP(A27,'Jurnal Penyesuai'!$R$4:$R$21,'Jurnal Penyesuai'!$S$4:$T$21),"")} -> 780000 | J27: 0 | K27: =IF(G27+I27-J27<0,"",G27+I27-J27) -> 780000 | L27: =IF(H27-I27+J27<0,"",IF((H27-I27+J27)-(G27+I27-J27)<0,"",(H27-I27+J27)-(G27+I27-J27))) | M27: =K27 -> 780000 | N27: =L27 | Q27: =IF(AND(M27="",O27=""),K27,"") | R27: =IF(AND(N27="",P27=""),L27,"")
A28: 601 | B28: Beban Perlengkapan Toko | E28: {=IFERROR(XLOOKUP(A28,'Jurnal Umum'!$C$119:$C$129,'Jurnal Umum'!$D$119:$E$129),"")} | G28: =IF(D28="",IF(C28+E28-F28<0,"",C28+E28-F28),"") -> 0 | H28: =IF(C28="",IF(D28-E28+F28<0,"",D28-E28+F28),"") -> 0 | I28: {=IFERROR(XLOOKUP(A28,'Jurnal Penyesuai'!$R$4:$R$21,'Jurnal Penyesuai'!$S$4:$T$21),"")} -> 520000 | J28: 0 | K28: =IF(G28+I28-J28<0,"",G28+I28-J28) -> 520000 | L28: =IF(H28-I28+J28<0,"",IF((H28-I28+J28)-(G28+I28-J28)<0,"",(H28-I28+J28)-(G28+I28-J28))) | M28: =K28 -> 520000 | N28: =L28 | Q28: =IF(AND(M28="",O28=""),K28,"") | R28: =IF(AND(N28="",P28=""),L28,"")
A29: 602 | B29: Beban Sewa | E29: {=IFERROR(XLOOKUP(A29,'Jurnal Umum'!$C$119:$C$129,'Jurnal Umum'!$D$119:$E$129),"")} | G29: =IF(D29="",IF(C29+E29-F29<0,"",C29+E29-F29),"") -> 0 | H29: =IF(C29="",IF(D29-E29+F29<0,"",D29-E29+F29),"") -> 0 | I29: {=IFERROR(XLOOKUP(A29,'Jurnal Penyesuai'!$R$4:$R$21,'Jurnal Penyesuai'!$S$4:$T$21),"")} -> 500000 | J29: 0 | K29: =IF(G29+I29-J29<0,"",G29+I29-J29) -> 500000 | L29: =IF(H29-I29+J29<0,"",IF((H29-I29+J29)-(G29+I29-J29)<0,"",(H29-I29+J29)-(G29+I29-J29))) | M29: =K29 -> 500000 | N29: =L29 | Q29: =IF(AND(M29="",O29=""),K29,"") | R29: =IF(AND(N29="",P29=""),L29,"")
A30: 603 | B30: Beban Iklan | E30: {=IFERROR(XLOOKUP(A30,'Jurnal Umum'!$C$119:$C$129,'Jurnal Umum'!$D$119:$E$129),"")} | G30: =IF(D30="",IF(C30+E30-F30<0,"",C30+E30-F30),"") -> 0 | H30: =IF(C30="",IF(D30-E30+F30<0,"",D30-E30+F30),"") -> 0 | I30: {=IFERROR(XLOOKUP(A30,'Jurnal Penyesuai'!$R$4:$R$21,'Jurnal Penyesuai'!$S$4:$T$21),"")} -> 400000 | J30: 0 | K30: =IF(G30+I30-J30<0,"",G30+I30-J30) -> 400000 | L30: =IF(H30-I30+J30<0,"",IF((H30-I30+J30)-(G30+I30-J30)<0,"",(H30-I30+J30)-(G30+I30-J30))) | M30: =K30 -> 400000 | N30: =L30 | Q30: =IF(AND(M30="",O30=""),K30,"") | R30: =IF(AND(N30="",P30=""),L30,"")
A31: 604 | B31: Beban Asuransi | E31: {=IFERROR(XLOOKUP(A31,'Jurnal Umum'!$C$119:$C$129,'Jurnal Umum'!$D$119:$E$129),"")} | G31: =IF(D31="",IF(C31+E31-F31<0,"",C31+E31-F31),"") -> 0 | H31: =IF(C31="",IF(D31-E31+F31<0,"",D31-E31+F31),"") -> 0 | I31: {=IFERROR(XLOOKUP(A31,'Jurnal Penyesuai'!$R$4:$R$21,'Jurnal Penyesuai'!$S$4:$T$21),"")} -> 25000 | J31: 0 | K31: =IF(G31+I31-J31<0,"",G31+I31-J31) -> 25000 | L31: =IF(H31-I31+J31<0,"",IF((H31-I31+J31)-(G31+I31-J31)<0,"",(H31-I31+J31)-(G31+I31-J31))) | M31: =K31 -> 25000 | N31: =L31 | Q31: =IF(AND(M31="",O31=""),K31,"") | R31: =IF(AND(N31="",P31=""),L31,"")
A32: 605 | B32: Beban Penyusutan Aktiva Tetap | E32: {=IFERROR(XLOOKUP(A32,'Jurnal Umum'!$C$119:$C$129,'Jurnal Umum'!$D$119:$E$129),"")} | G32: =IF(D32="",IF(C32+E32-F32<0,"",C32+E32-F32),"") -> 0 | H32: =IF(C32="",IF(D32-E32+F32<0,"",D32-E32+F32),"") -> 0 | I32: {=IFERROR(XLOOKUP(A32,'Jurnal Penyesuai'!$R$4:$R$21,'Jurnal Penyesuai'!$S$4:$T$21),"")} -> 336600000 | J32: 0 | K32: =IF(G32+I32-J32<0,"",G32+I32-J32) -> 336600000 | L32: =IF(H32-I32+J32<0,"",IF((H32-I32+J32)-(G32+I32-J32)<0,"",(H32-I32+J32)-(G32+I32-J32))) | M32: =K32 -> 336600000 | N32: =L32 | Q32: =IF(AND(M32="",O32=""),K32,"") | R32: =IF(AND(N32="",P32=""),L32,"")
A33: 606 | B33: Beban Gaji Kantor | C33: 280500000 | E33: {=IFERROR(XLOOKUP(A33,'Jurnal Umum'!$C$119:$C$129,'Jurnal Umum'!$D$119:$E$129),"")} | G33: =IF(D33="",IF(C33+E33-F33<0,"",C33+E33-F33),"") -> 280500000 | H33: =IF(C33="",IF(D33-E33+F33<0,"",D33-E33+F33),"") | I33: {=IFERROR(XLOOKUP(A33,'Jurnal Penyesuai'!$R$4:$R$21,'Jurnal Penyesuai'!$S$4:$T$21),"")} | K33: =IF(G33+I33-J33<0,"",G33+I33-J33) -> 280500000 | L33: =IF(H33-I33+J33<0,"",IF((H33-I33+J33)-(G33+I33-J33)<0,"",(H33-I33+J33)-(G33+I33-J33))) | M33: =K33 -> 280500000 | N33: =L33 | Q33: =IF(AND(M33="",O33=""),K33,"") | R33: =IF(AND(N33="",P33=""),L33,"")
A34: 607 | B34: Beban Asuransi | C34: 187000000 | E34: {=IFERROR(XLOOKUP(A34,'Jurnal Umum'!$C$119:$C$129,'Jurnal Umum'!$D$119:$E$129),"")} | G34: =IF(D34="",IF(C34+E34-F34<0,"",C34+E34-F34),"") -> 187000000 | H34: =IF(C34="",IF(D34-E34+F34<0,"",D34-E34+F34),"") | I34: {=IFERROR(XLOOKUP(A34,'Jurnal Penyesuai'!$R$4:$R$21,'Jurnal Penyesuai'!$S$4:$T$21),"")} | K34: =IF(G34+I34-J34<0,"",G34+I34-J34) -> 187000000 | L34: =IF(H34-I34+J34<0,"",IF((H34-I34+J34)-(G34+I34-J34)<0,"",(H34-I34+J34)-(G34+I34-J34))) | M34: =K34 -> 187000000 | N34: =L34 | Q34: =IF(AND(M34="",O34=""),K34,"") | R34: =IF(AND(N34="",P34=""),L34,"")
A35: 608 | B35: Beban Air, Listrik dan Telepon | C35: 9800000 | E35: {=IFERROR(XLOOKUP(A35,'Jurnal Umum'!$C$119:$C$129,'Jurnal Umum'!$D$119:$E$129),"")} -> 450000 | F35: 0 | G35: =IF(D35="",IF(C35+E35-F35<0,"",C35+E35-F35),"") -> 10250000 | H35: =IF(C35="",IF(D35-E35+F35<0,"",D35-E35+F35),"") | I35: {=IFERROR(XLOOKUP(A35,'Jurnal Penyesuai'!$R$4:$R$21,'Jurnal Penyesuai'!$S$4:$T$21),"")} | K35: =IF(G35+I35-J35<0,"",G35+I35-J35) -> 10250000 | L35: =IF(H35-I35+J35<0,"",IF((H35-I35+J35)-(G35+I35-J35)<0,"",(H35-I35+J35)-(G35+I35-J35))) | M35: =K35 -> 10250000 | N35: =L35 | Q35: =IF(AND(M35="",O35=""),K35,"") | R35: =IF(AND(N35="",P35=""),L35,"")
A36: 609 | B36: Beban Administrasi Bank | E36: {=IFERROR(XLOOKUP(A36,'Jurnal Umum'!$C$119:$C$129,'Jurnal Umum'!$D$119:$E$129),"")} | G36: =IF(D36="",IF(C36+E36-F36<0,"",C36+E36-F36),"") -> 0 | H36: =IF(C36="",IF(D36-E36+F36<0,"",D36-E36+F36),"") -> 0 | I36: {=IFERROR(XLOOKUP(A36,'Jurnal Penyesuai'!$R$4:$R$21,'Jurnal Penyesuai'!$S$4:$T$21),"")} -> 1010000 | J36: 0 | K36: =IF(G36+I36-J36<0,"",G36+I36-J36) -> 1010000 | L36: =IF(H36-I36+J36<0,"",IF((H36-I36+J36)-(G36+I36-J36)<0,"",(H36-I36+J36)-(G36+I36-J36))) | M36: =K36 -> 1010000 | N36: =L36 | Q36: =IF(AND(M36="",O36=""),K36,"") | R36: =IF(AND(N36="",P36=""),L36,"")
A37: 610 | B37: Beban PPH 21 | E37: {=IFERROR(XLOOKUP(A37,'Jurnal Umum'!$C$119:$C$129,'Jurnal Umum'!$D$119:$E$129),"")} | G37: =IF(D37="",IF(C37+E37-F37<0,"",C37+E37-F37),"") -> 0 | H37: =IF(C37="",IF(D37-E37+F37<0,"",D37-E37+F37),"") -> 0 | I37: {=IFERROR(XLOOKUP(A37,'Jurnal Penyesuai'!$R$4:$R$21,'Jurnal Penyesuai'!$S$4:$T$21),"")} -> 80000 | J37: 0 | K37: =IF(G37+I37-J37<0,"",G37+I37-J37) -> 80000 | L37: =IF(H37-I37+J37<0,"",IF((H37-I37+J37)-(G37+I37-J37)<0,"",(H37-I37+J37)-(G37+I37-J37))) | M37: =K37 -> 80000 | N37: =L37 | Q37: =IF(AND(M37="",O37=""),K37,"") | R37: =IF(AND(N37="",P37=""),L37,"")
A38: 700 | B38: Pendapatan Bunga | D38: 15000000 | E38: {=IFERROR(XLOOKUP(A38,'Jurnal Umum'!$C$119:$C$129,'Jurnal Umum'!$D$119:$E$129),"")} | G38: =IF(D38="",IF(C38+E38-F38<0,"",C38+E38-F38),"") | H38: =IF(C38="",IF(D38-E38+F38<0,"",D38-E38+F38),"") -> 15000000 | I38: {=IFERROR(XLOOKUP(A38,'Jurnal Penyesuai'!$R$4:$R$21,'Jurnal Penyesuai'!$S$4:$T$21),"")} -> 0 | J38: 2000000 | K38: =IF(G38+I38-J38<0,"",G38+I38-J38) | L38: =J38+H38 -> 17000000 | M38: =K38 | N38: =L38 -> 17000000 | Q38: =IF(AND(M38="",O38=""),K38,"") | R38: =IF(AND(N38="",P38=""),L38,"")
A39: Total | C39: =SUM(C3:C38) -> 6929850000 | D39: =SUM(D3:D38) -> 6929850000 | E39: =SUM(E3:E38) -> 17991200 | F39: =SUM(F2:F38) -> 17991200 | G39: =SUM(G5:G38) -> 6931301200 | H39: =SUM(H5:H38) -> 6931301200 | I39: =SUM(I5:I38) -> 383655000 | J39: =SUM(J5:J38) -> 383655000 | K39: =SUM(K5:K38) -> 7269981200 | L39: =SUM(L5:L38) -> 7269981200 | M39: =SUM(M2:M38) -> 3680096200 | N39: =SUM(N2:N38) -> 4311640000 | O39: =SUM(O2:O38) -> 0 | P39: =SUM(P2:P38) -> 0 | Q39: =SUM(Q2:Q38) -> 3589885000 | R39: =SUM(R2:R38) -> 2958341200
J40: =IF(M40=R40,"Retained Earnings",if(N40=Q40,"Retained Loss","Wrong")) -> Retained Earnings | M40: =IF(N39-M39<0,"",N39-M39) -> 631543800 | N40: =IF(M39-N39<0,"",M39-N39) | Q40: =IF(R39-Q39<0,"",R39-Q39) | R40: =IF(Q39-R39<0,"",Q39-R39) -> 631543800

Sheet LAPORAN KEUANGAN
B2: PT Gunung Semeru | G2: PT Gunung Semeru
B3: Jl. Pulo Gundul No. 12 | G3: Jl. Pulo Gundul No. 12
B4: Jakarta Pusat | G4: Jakarta Pusat
B5: Pendapatan Bunga | C5: {=XLOOKUP(B5,'NERACA penyesuai'!B5:B38,'NERACA penyesuai'!C5:D38)} | D5: 17000000 | G5: Modal Awal
B6: Penjualan | C6: {=XLOOKUP(B6,'NERACA penyesuai'!B6:B39,'NERACA penyesuai'!C6:D39)} -> 0 | D6: 4287640000 | H6: Modal Saham | I6: {=XLOOKUP(H6,'NERACA penyesuai'!$B$5:$B$38,'NERACA penyesuai'!$C$5:$D$38)} -> 0 | J6: 1000000000
B7: Retur Penjualan | C7: {=XLOOKUP(B7,'NERACA penyesuai'!B7:B40,'NERACA penyesuai'!C7:D40)} -> 5000000 | G7: Perubahan
E8: =D5+D6-C7 -> 4299640000 | H8: Agio Saham | I8: {=XLOOKUP(H8,'NERACA penyesuai'!$B$5:$B$38,'NERACA penyesuai'!$C$5:$D$38)} -> 0 | J8: 156830000
B9: HPP | H9: Laba Ditahan | I9: 0 | J9: =400000000+Lajur!M40 -> 1031543800
B10: Persediaan | C10: {=XLOOKUP("Persediaan Barang Dagang",'NERACA penyesuai'!B:B,'NERACA penyesuai'!C:D)} -> 20850000 | H10: Ikhtisar Laba Rugi | I10: {=XLOOKUP(H10,'NERACA penyesuai'!$B$5:$B$38,'NERACA penyesuai'!$C$5:$D$38)} -> 2150000
B11: Pembelian | C11: {=XLOOKUP(B11,'NERACA penyesuai'!B:B,'NERACA penyesuai'!C:D)} -> 2857431200 | G11: Total Modal | J11: =sum(J5:J10,-I10) -> 2186223800
B12: Retur Pembelian | C12: {=XLOOKUP(B12,'NERACA penyesuai'!B:B,'NERACA penyesuai'!C:D)} -> 0 | D12: 7000000
E13: =sum(C10,C11,-D12) -> 2871281200
G14: PT GUNUNG SEMERU
B15: Beban
B16: Beban Perlengkapan Kantor | C16: {=XLOOKUP(B16,'NERACA penyesuai'!B:B,'NERACA penyesuai'!C:D)} -> 780000 | G16: PERKIRAAN BUKU BESAR | I16: DEBET | J16: KREDIT
B17: Beban Perlengkapan Toko | C17: {=XLOOKUP(B17,'NERACA penyesuai'!B:B,'NERACA penyesuai'!C:D)} -> 520000 | G17: 100 | H17: Kas Di Bank | I17: =Lajur!Q5 -> 136000000 | J17: =Lajur!R5
B18: Beban Sewa | C18: {=XLOOKUP(B18,'NERACA penyesuai'!B:B,'NERACA penyesuai'!C:D)} -> 500000 | G18: 101 | H18: Kas Kecil | I18: =Lajur!Q6 -> 3170000 | J18: =Lajur!R6
B19: Beban Iklan | C19: {=XLOOKUP(B19,'NERACA penyesuai'!B:B,'NERACA penyesuai'!C:D)} -> 400000 | G19: 102 | H19: Piutang Dagang | I19: =Lajur!Q7 -> 2640000 | J19: =Lajur!R7
B20: Beban Penyusutan Aktiva Tetap | C20: {=XLOOKUP(B20,'NERACA penyesuai'!B:B,'NERACA penyesuai'!C:D)} -> 336600000 | G20: 103 | H20: Persediaan Barang Dagang | I20: =Lajur!Q8 -> 20850000 | J20: =Lajur!R8
B21: Beban Asuransi | C21: 187000000 | G21: 104 | H21: Perlengkapan | I21: =Lajur!Q9 -> 700000 | J21: =Lajur!R9
B22: Beban Gaji Kantor | C22: {=XLOOKUP(B22,'NERACA penyesuai'!B:B,'NERACA penyesuai'!C:D)} -> 280500000 | G22: 105 | H22: Sewa Gudang Dibayar Dimuka | I22: =Lajur!Q10 -> 0 | J22: =Lajur!R10
B23: Beban Asuransi | C23: {=XLOOKUP(B23,'NERACA penyesuai'!B:B,'NERACA penyesuai'!C:D)} -> 25000 | G23: 106 | H23: Iklan Dibayar Dimuka | I23: =Lajur!Q11 -> 100000 | J23: =Lajur!R11
B24: Beban Air, Listrik dan Telepon | C24: {=XLOOKUP(B24,'NERACA penyesuai'!B:B,'NERACA penyesuai'!C:D)} -> 10250000 | G24: 107 | H24: Asuransi Dibayar Dimuka | I24: =Lajur!Q12 -> 275000 | J24: =Lajur!R12
B25: Beban Administrasi Bank | C25: {=XLOOKUP(B25,'NERACA penyesuai'!B:B,'NERACA penyesuai'!C:D)} -> 1010000 | G25: 108 | H25: Aktiva Tetap | I25: =Lajur!Q13 -> 3424000000 | J25: =Lajur!R13
B26: Beban PPh 21 | C26: {=XLOOKUP(B26,'NERACA penyesuai'!B:B,'NERACA penyesuai'!C:D)} -> 80000 | G26: 109 | H26: Akumulasi Penyusutan Aktiva Tetap | I26: =Lajur!Q14 | J26: =Lajur!R14 -> 1401000000
E27: =SUM(C16:C26) -> 817665000 | G27: 200 | H27: Utang Dagang | I27: =Lajur!Q15 -> 0 | J27: =Lajur!R15 -> 431200
E28: =SUM(E8:E23,-E27) -> 6353256200 | G28: 201 | H28: Utang PPH 21 | I28: =Lajur!Q16 | J28: =Lajur!R16 -> 80000
G29: 202 | H29: Utang Gaji | I29: =Lajur!Q17 -> 0 | J29: =Lajur!R17 -> 0
G30: 203 | H30: Utang Air, Listrik, dan Telepon | I30: =Lajur!Q18 -> 0 | J30: =Lajur!R18 -> 0
G31: 300 | H31: Modal Saham | I31: =Lajur!Q19 -> 0 | J31: =Lajur!R19 -> 1000000000
G32: 301 | H32: Agio Saham | I32: =Lajur!Q20 -> 0 | J32: =Lajur!R20 -> 156830000
G33: 302 | H33: Laba Ditahan | I33: =Lajur!Q21 -> 0 | J33: =Lajur!R21+Lajur!M40 -> 1031543800
G34: 303 | H34: Ikhtisar Laba Rugi | I34: =Lajur!Q22 -> 2150000
I35: =SUM(I17:I34) -> 3589885000 | J35: =SUM(J17:J34) -> 3589885000

Sheet Closing Entries
B4: PT Gunung Semeru
B5: Jl. Pulo Gundul No. 12
B6: Jakarta Selatan
B8: DATE | C8: ACC. NO | D8: DESCRIPTION | F8: DEBET | G8: CREDIT
B10: 45412 | C10: {=iferror(if(D10<>"",XLOOKUP(D10,Lajur!B:B,Lajur!A:A),if(E10<>"",XLOOKUP(E10,Lajur!B:B,Lajur!A:A),"")),"")} -> 700 | D10: Pendapatan Bunga | F10: 17000000
C11: {=iferror(if(D11<>"",XLOOKUP(D11,Lajur!B:B,Lajur!A:A),if(E11<>"",XLOOKUP(E11,Lajur!B:B,Lajur!A:A),"")),"")} -> 400 | D11: Penjualan | F11: 4287640000
C12: {=iferror(if(D12<>"",XLOOKUP(D12,Lajur!B:B,Lajur!A:A),if(E12<>"",XLOOKUP(E12,Lajur!B:B,Lajur!A:A),"")),"")} -> 501 | D12: Retur Pembelian | F12: 7000000
C13: {=iferror(if(D13<>"",XLOOKUP(D13,Lajur!B:B,Lajur!A:A),if(E13<>"",XLOOKUP(E13,Lajur!B:B,Lajur!A:A),"")),"")} -> 303 | E13: Ikhtisar Laba Rugi | G13: =sum(F10:F12) -> 4311640000
C14: {=iferror(if(D14<>"",XLOOKUP(D14,Lajur!B:B,Lajur!A:A),if(E14<>"",XLOOKUP(E14,Lajur!B:B,Lajur!A:A),"")),"")} -> 303 | D14: Ikhtisar Laba Rugi | F14: =sum(G15:G28) -> 3680096200
B15: 45412 | C15: {=iferror(if(D15<>"",XLOOKUP(D15,Lajur!B:B,Lajur!A:A),if(E15<>"",XLOOKUP(E15,Lajur!B:B,Lajur!A:A),"")),"")} -> 401 | E15: Retur Penjualan | G15: {=XLOOKUP(C15,Lajur!A:A,Lajur!M:M)} -> 5000000
C16: {=iferror(if(D16<>"",XLOOKUP(D16,Lajur!B:B,Lajur!A:A),if(E16<>"",XLOOKUP(E16,Lajur!B:B,Lajur!A:A),"")),"")} -> 500 | E16: Pembelian | G16: {=XLOOKUP(C16,Lajur!A:A,Lajur!M:M)} -> 2857431200
C17: {=iferror(if(D17<>"",XLOOKUP(D17,Lajur!B:B,Lajur!A:A),if(E17<>"",XLOOKUP(E17,Lajur!B:B,Lajur!A:A),"")),"")} -> 103 | E17: Persediaan Barang Dagang | G17: {=XLOOKUP(C17,Lajur!A:A,Lajur!M:M)}
C18: {=iferror(if(D18<>"",XLOOKUP(D18,Lajur!B:B,Lajur!A:A),if(E18<>"",XLOOKUP(E18,Lajur!B:B,Lajur!A:A),"")),"")} -> 600 | E18: Beban Perlengkapan Kantor | G18: {=XLOOKUP(C18,Lajur!A:A,Lajur!M:M)} -> 780000
C19: {=iferror(if(D19<>"",XLOOKUP(D19,Lajur!B:B,Lajur!A:A),if(E19<>"",XLOOKUP(E19,Lajur!B:B,Lajur!A:A),"")),"")} -> 601 | E19: Beban Perlengkapan Toko | G19: {=XLOOKUP(C19,Lajur!A:A,Lajur!M:M)} -> 520000
C20: {=iferror(if(D20<>"",XLOOKUP(D20,Lajur!B:B,Lajur!A:A),if(E20<>"",XLOOKUP(E20,Lajur!B:B,Lajur!A:A),"")),"")} -> 602 | E20: Beban Sewa | G20: {=XLOOKUP(C20,Lajur!A:A,Lajur!M:M)} -> 500000
C21: {=iferror(if(D21<>"",XLOOKUP(D21,Lajur!B:B,Lajur!A:A),if(E21<>"",XLOOKUP(E21,Lajur!B:B,Lajur!A:A),"")),"")} -> 603 | E21: Beban Iklan | G21: {=XLOOKUP(C21,Lajur!A:A,Lajur!M:M)} -> 400000
C22: {=iferror(if(D22<>"",XLOOKUP(D22,Lajur!B:B,Lajur!A:A),if(E22<>"",XLOOKUP(E22,Lajur!B:B,Lajur!A:A),"")),"")} -> 604 | E22: Beban Asuransi | G22: {=XLOOKUP(C22,Lajur!A:A,Lajur!M:M)} -> 25000
C23: {=iferror(if(D23<>"",XLOOKUP(D23,Lajur!B:B,Lajur!A:A),if(E23<>"",XLOOKUP(E23,Lajur!B:B,Lajur!A:A),"")),"")} -> 605 | E23: Beban Penyusutan Aktiva Tetap | G23: {=XLOOKUP(C23,Lajur!A:A,Lajur!M:M)} -> 336600000
C24: {=iferror(if(D24<>"",XLOOKUP(D24,Lajur!B:B,Lajur!A:A),if(E24<>"",XLOOKUP(E24,Lajur!B:B,Lajur!A:A),"")),"")} -> 606 | E24: Beban Gaji Kantor | G24: {=XLOOKUP(C24,Lajur!A:A,Lajur!M:M)} -> 280500000
C25: 607 | E25: Beban Asuransi | G25: {=XLOOKUP(C25,Lajur!A:A,Lajur!M:M)} -> 187000000
C26: {=iferror(if(D26<>"",XLOOKUP(D26,Lajur!B:B,Lajur!A:A),if(E26<>"",XLOOKUP(E26,Lajur!B:B,Lajur!A:A),"")),"")} -> 608 | E26: Beban Air, Listrik dan Telepon | G26: {=XLOOKUP(C26,Lajur!A:A,Lajur!M:M)} -> 10250000
C27: {=iferror(if(D27<>"",XLOOKUP(D27,Lajur!B:B,Lajur!A:A),if(E27<>"",XLOOKUP(E27,Lajur!B:B,Lajur!A:A),"")),"")} -> 609 | E27: Beban Administrasi Bank | G27: {=XLOOKUP(C27,Lajur!A:A,Lajur!M:M)} -> 1010000
C28: {=iferror(if(D28<>"",XLOOKUP(D28,Lajur!B:B,Lajur!A:A),if(E28<>"",XLOOKUP(E28,Lajur!B:B,Lajur!A:A),"")),"")} -> 610 | E28: Beban PPH 21 | G28: {=XLOOKUP(C28,Lajur!A:A,Lajur!M:M)} -> 80000
F29: =SUM(F10:F28) -> 7991736200 | G29: =SUM(G10:G28) -> 7991736200
B31: Entertainment Expense | C31: 25000
B32: Office Supplies | C32: =960000+120000 -> 1080000
B33: Other Expense | C33: 150000 | E33: RECAPITULATION
E34: ACC NO. | F34: DEBET | G34: CREDIT
E35: {=tocol(SORT(UNIQUE(C10:C28),1,TRUE),1,0)} -> 103 | F35: =SUMIF($C$7:$C$28,E34,$F$7:$F$28) -> 0 | G35: =SUMIF($C$7:$C$28,E35,$G$7:$G$28) -> 0
E36: 303 | F36: =SUMIF($C$7:$C$28,E36,$F$7:$F$28) -> 3680096200 | G36: =SUMIF($C$7:$C$28,E36,$G$7:$G$28) -> 4311640000
E37: 400 | F37: =SUMIF($C$7:$C$28,E37,$F$7:$F$28) -> 4287640000 | G37: =SUMIF($C$7:$C$28,E37,$G$7:$G$28) -> 0
E38: 401 | F38: =SUMIF($C$7:$C$28,E38,$F$7:$F$28) -> 0 | G38: =SUMIF($C$7:$C$28,E38,$G$7:$G$28) -> 5000000
E39: 500 | F39: =SUMIF($C$7:$C$28,E39,$F$7:$F$28) -> 0 | G39: =SUMIF($C$7:$C$28,E39,$G$7:$G$28) -> 2857431200
E40: 501 | F40: =SUMIF($C$7:$C$28,E40,$F$7:$F$28) -> 7000000 | G40: =SUMIF($C$7:$C$28,E40,$G$7:$G$28) -> 0
E41: 600 | F41: =SUMIF($C$7:$C$28,E41,$F$7:$F$28) -> 0 | G41: =SUMIF($C$7:$C$28,E41,$G$7:$G$28) -> 780000
E42: 601 | F42: =SUMIF($C$7:$C$28,E42,$F$7:$F$28) -> 0 | G42: =SUMIF($C$7:$C$28,E42,$G$7:$G$28) -> 520000
E43: 602 | F43: =SUMIF($C$7:$C$28,E43,$F$7:$F$28) -> 0 | G43: =SUMIF($C$7:$C$28,E43,$G$7:$G$28) -> 500000
E44: 603 | F44: =SUMIF($C$7:$C$28,E44,$F$7:$F$28) -> 0 | G44: =SUMIF($C$7:$C$28,E44,$G$7:$G$28) -> 400000
E45: 604 | F45: =SUMIF($C$7:$C$28,E45,$F$7:$F$28) -> 0 | G45: =SUMIF($C$7:$C$28,E45,$G$7:$G$28) -> 25000
E46: 605 | F46: =SUMIF($C$7:$C$28,E46,$F$7:$F$28) -> 0 | G46: =SUMIF($C$7:$C$28,E46,$G$7:$G$28) -> 336600000
E47: 606 | F47: =SUMIF($C$7:$C$28,E47,$F$7:$F$28) -> 0 | G47: =SUMIF($C$7:$C$28,E47,$G$7:$G$28) -> 280500000
... E52: 700 | F52: =SUMIF($C$7:$C$28,E52,$F$7:$F$28) -> 17000000 | G52: =SUMIF($C$7:$C$28,E52,$G$7:$G$28) -> 0
E53: TOTAL | F53: =SUM(F35:F52) -> 7991736200 | G53: =SUM(G35:G52) -> 7991736200
